Workbook
Name TiposDeFuncao: 'Deflatores Sisp'!$M$37:$M$70
Name TiposDeManutencao: 'Deflatores Sisp'!$G$4:$G$38

Sheet Capa
D2: Planilha de Contagem de Pontos de Função - Versão 2025.01
E3: Roteiro de Métricas de Software do SISP V.2.3
B4: Identificação da Contagem
C6: Projeto/Demanda | D6: PGF - Fase 1
C8: Aplicação | D8: PGF - Plataforma de Gestão Financeira
C10: Responsável | D10: Prodesp
C12: Tipo de Contagem | D12: Projeto de Desenvolvimento
C14: Forma de Contagem | D14: Detalhada
B16: Tamanho em Pontos de Função
B17: Pontos de Função (IFPUG) | D17: ? | E17: =SUM('Deflatores Sisp'!$J$4:$J$38) -> 481
B18: Manutenção Corretiva (Legado ou S/ Garantia) | E18: =SUMIF('Deflatores Sisp'!$M$4:$M$38,"CORRETIVA",'Deflatores Sisp'!$K$4:$K$38) -> 0
B19: Manutenção Adaptativa | E19: =SUMIF('Deflatores Sisp'!$M$4:$M$38,"ADAPTATIVA",'Deflatores Sisp'!$K$4:$K$38) -> 0
B20: Melhoria Evolutiva - Func. Incluídas | E20: =SUMIF('Deflatores Sisp'!$M$4:$M$38,"EvolutivaI",'Deflatores Sisp'!$K$4:$K$38) -> 481
B21: Melhoria Evolutiva - Func. Alteradas | E21: =SUMIF('Deflatores Sisp'!$M$4:$M$38,"EvolutivaA",'Deflatores Sisp'!$K$4:$K$38) -> 0
B22: Melhoria Evolutiva - Func. Excluídas | E22: =SUMIF('Deflatores Sisp'!$M$4:$M$38,"EvolutivaE",'Deflatores Sisp'!$K$4:$K$38) -> 0
B23: Tamanho Funcional Ajustado | E23: ='Deflatores Sisp'!N2 -> 24.05
B24: Requisitos Técnicos (Correlação com Guia Local) | E24: =SUM('Deflatores Sisp'!$K$42:$K$70) -> 0
B25: Total Pontos de Função (Tamanho Funcional Ajustado + Requisitos Não Funcionais) | E25: =Funções!O6 -> 232.39
B27: Escopo geral da contagem
B28: Planilha para controle das medições do PGF Fase 1
B32: Histórico do Documento
B33: Data | C33: Versão | D33: Descrição | E33: Autor
B34: 46043 | C34: 1.0 | D34: Criação da planilha e inclusão das contagens das Sprints iniciais para entrada em produção do Sistema | E34: Levi Barros Nóbrega

Sheet Funções
A1: Planilha de contagem de ponto de função - Versão 1.0
A4: =Capa!C6&" : "&Capa!D6 -> Projeto/Demanda : PGF - Fase 1 | C4: =Capa!C12&" : "&Capa!D12 -> Tipo de Contagem : Projeto de Desenvolvimento
A5: =Capa!C8&" : "&Capa!D8 -> Aplicação : PGF - Plataforma de Gestão Financeira | C5: =Capa!C14&" : "&Capa!D14 -> Forma de Contagem : Detalhada | K5: Total PF IFPUG | N5: PF Local do EM | O5: Total PF Ajustado | P5: Fases/Disciplinas
A6: =Capa!C10&" : "&Capa!D10 -> Responsável : Prodesp | K6: =SUM($K$8:$K$121643) -> 980 | N6: =SUM($N$8:$N$104) -> 481 | O6: =SUM(O8:O1029143) -> 232.39
A7: Medição / Sprint / Tarefa | B7: Detalhes / Nome da Função | C7: Tipo | D7: Manutenção | E7: TD | F7: Descr TD | G7: AR/TR | H7: Descr AR/TR | I7: Complex. | J7: ctl | K7: PF IFPUG | L7: C | M7: ctl2 | N7: PF Local do EM | O7: PF Ajustado | P7: Requisitos (25%) | Q7: Projeto (10%) | R7: Implementação (40%) | S7: Teste (15%) | T7: Homologação (5%) | U7: Implantação (5%) | V7: Não se aplica | W7: % Percentual por Disciplina | X7: Referência | Y7: Observações
A8: Medição 02 (M02) | B8: Tarefas da Medição 02 - Fevereiro/2026 | I8: =IF(ISBLANK(C8),"",IF(L8="L","Baixa",IF(L8="A","Média",IF(L8="","","Alta")))) | J8: =CONCATENATE(C8,L8) | K8: =IF(ISBLANK(C8),"",IF(C8="ALI",IF(L8="L",7,IF(L8="A",10,15)),IF(C8="AIE",IF(L8="L",5,IF(L8="A",7,10)),IF(C8="SE",IF(L8="L",4,IF(L8="A",5,7)),IF(OR(C8="EE",C8="CE"),IF(L8="L",3,IF(L8="A",4,6)),0))))) | L8: =IF(OR(ISBLANK(E8),ISBLANK(G8)),IF(OR(C8="ALI",C8="AIE"),"L",IF(OR(C8="EE",C8="SE",C8="CE"),"A","")),IF(C8="EE",IF(G8>=3,IF(E8>=5,"H","A"),IF(G8>=2,IF(E8>=16,"H",IF(E8<=4,"L","A")),IF(E8<=15,"L","A"))),IF(OR(C8="SE",C8="CE"),IF(G8>=4,IF(E8>=6,"H","A"),IF(G8>=2,IF(E8>=20,"H",IF(E8<=5,"L","A")),IF(E8<=19,"L","A"))),IF(OR(C8="ALI",C8="AIE"),IF(G8>=6,IF(E8>=20,"H","A"),IF(G8>=2,IF(E8>=51,"H",IF(E8<=19,"L","A")),IF(E8<=50,"L","A"))),"")))) | M8: =CONCATENATE(C8,D8) | N8: =IF(OR(K8="",K8=0),O8,K8) | O8: =IFERROR(IF(NOT(ISERROR(VLOOKUP(C8,'Deflatores Sisp'!G$42:H$70,2,FALSE))),VLOOKUP(C8,'Deflatores Sisp'!G$42:H$70,2,FALSE),IF(OR(ISBLANK(D8),ISBLANK(C8)),"",VLOOKUP(D8,'Deflatores Sisp'!G$4:H$38,2,FALSE)*K8+VLOOKUP(D8,'Deflatores Sisp'!G$4:I$38,3,FALSE)))*W8,"") | T8: x | W8: =IF(V8="",SUM(Z8:AE8),IF(C8="PA",E8,100%)) -> 0.05 | Z8: =IF(P8="x",25%,0) -> 0 | AA8: =IF(Q8="x",10%,0) -> 0 | AB8: =IF(R8="x",40%,0) -> 0 | AC8: =IF(S8="x",15%,0) -> 0 | AD8: =IF(T8="x",5%,0) -> 0.05 | AE8: =IF(U8="x",5%,0) -> 0
B9: Clientes_e_Enderecos | C9: ALI | D9: I | E9: 18 | F9: TR 1 – Cliente (clientes) TD (12): id (uuid), cpf_cnpj (text), nome_razao_social (text), email (text), telefone (text), tipo_cliente (text), status (text), user_id (uuid), data_cadastro (timestamp), created_at (timestamp), updated_at (timestamp). TR 2 – Endereço de Cobrança (endereco_cobranca JSONB) TD (6): logradouro, numero, complemento, bairro, cidade, uf, cep. | G9: 2 | H9: (1) Cliente – dados cadastrais principais do cliente PF/PJ; (2) Endereço de Cobrança – estrutura JSONB contendo endereço completo para faturamento. | I9: =IF(ISBLANK(C9),"",IF(L9="L","Baixa",IF(L9="A","Média",IF(L9="","","Alta")))) -> Baixa | J9: =CONCATENATE(C9,L9) -> ALIL | K9: =IF(ISBLANK(C9),"",IF(C9="ALI",IF(L9="L",7,IF(L9="A",10,15)),IF(C9="AIE",IF(L9="L",5,IF(L9="A",7,10)),IF(C9="SE",IF(L9="L",4,IF(L9="A",5,7)),IF(OR(C9="EE",C9="CE"),IF(L9="L",3,IF(L9="A",4,6)),0))))) -> 7 | L9: =IF(OR(ISBLANK(E9),ISBLANK(G9)),IF(OR(C9="ALI",C9="AIE"),"L",IF(OR(C9="EE",C9="SE",C9="CE"),"A","")),IF(C9="EE",IF(G9>=3,IF(E9>=5,"H","A"),IF(G9>=2,IF(E9>=16,"H",IF(E9<=4,"L","A")),IF(E9<=15,"L","A"))),IF(OR(C9="SE",C9="CE"),IF(G9>=4,IF(E9>=6,"H","A"),IF(G9>=2,IF(E9>=20,"H",IF(E9<=5,"L","A")),IF(E9<=19,"L","A"))),IF(OR(C9="ALI",C9="AIE"),IF(G9>=6,IF(E9>=20,"H","A"),IF(G9>=2,IF(E9>=51,"H",IF(E9<=19,"L","A")),IF(E9<=50,"L","A"))),"")))) -> L | M9: =CONCATENATE(C9,D9) -> ALII | N9: =IF(OR(K9="",K9=0),O9,K9) -> 7 | O9: =IFERROR(IF(NOT(ISERROR(VLOOKUP(C9,'Deflatores Sisp'!G$42:H$70,2,FALSE))),VLOOKUP(C9,'Deflatores Sisp'!G$42:H$70,2,FALSE),IF(OR(ISBLANK(D9),ISBLANK(C9)),"",VLOOKUP(D9,'Deflatores Sisp'!G$4:H$38,2,FALSE)*K9+VLOOKUP(D9,'Deflatores Sisp'!G$4:I$38,3,FALSE)))*W9,"") -> 0.35 | T9: x | W9: =IF(V9="",SUM(Z9:AE9),IF(C9="PA",E9,100%)) -> 0.05 | Z9: =IF(P9="x",25%,0) -> 0 | AA9: =IF(Q9="x",10%,0) -> 0 | AB9: =IF(R9="x",40%,0) -> 0 | AC9: =IF(S9="x",15%,0) -> 0 | AD9: =IF(T9="x",5%,0) -> 0.05 | AE9: =IF(U9="x",5%,0) -> 0
B10: Usuarios_Profiles_Roles | C10: ALI | D10: I | E10: 16 | F10: TR 1 – Perfil de Usuário (profiles) TD (8): id (uuid), email (text), nome (text), cpf_cnpj (text), telefone (text), avatar_url (text), created_at (timestamp), updated_at (timestamp). TR 2 – Papéis do Usuário (user_roles) TD (4): id (uuid), user_id (uuid), role (app_role), created_at (timestamp). TR 3 – Perfil-Usuário (usuario_perfis) TD (4): id (uuid), user_id (uuid), perfil_id (uuid), created_at (timestamp). | G10: 3 | H10: (1) Profiles – dados de perfil vinculados ao auth.users; (2) User Roles – papéis do sistema (admin, comercial, financeiro, cliente); (3) Usuario Perfis – vínculo com perfis customizados para permissões granulares. | I10: =IF(ISBLANK(C10),"",IF(L10="L","Baixa",IF(L10="A","Média",IF(L10="","","Alta")))) -> Baixa | J10: =CONCATENATE(C10,L10) -> ALIL | K10: =IF(ISBLANK(C10),"",IF(C10="ALI",IF(L10="L",7,IF(L10="A",10,15)),IF(C10="AIE",IF(L10="L",5,IF(L10="A",7,10)),IF(C10="SE",IF(L10="L",4,IF(L10="A",5,7)),IF(OR(C10="EE",C10="CE"),IF(L10="L",3,IF(L10="A",4,6)),0))))) -> 7 | L10: =IF(OR(ISBLANK(E10),ISBLANK(G10)),IF(OR(C10="ALI",C10="AIE"),"L",IF(OR(C10="EE",C10="SE",C10="CE"),"A","")),IF(C10="EE",IF(G10>=3,IF(E10>=5,"H","A"),IF(G10>=2,IF(E10>=16,"H",IF(E10<=4,"L","A")),IF(E10<=15,"L","A"))),IF(OR(C10="SE",C10="CE"),IF(G10>=4,IF(E10>=6,"H","A"),IF(G10>=2,IF(E10>=20,"H",IF(E10<=5,"L","A")),IF(E10<=19,"L","A"))),IF(OR(C10="ALI",C10="AIE"),IF(G10>=6,IF(E10>=20,"H","A"),IF(G10>=2,IF(E10>=51,"H",IF(E10<=19,"L","A")),IF(E10<=50,"L","A"))),"")))) -> L | M10: =CONCATENATE(C10,D10) -> ALII | N10: =IF(OR(K10="",K10=0),O10,K10) -> 7 | O10: =IFERROR(IF(NOT(ISERROR(VLOOKUP(C10,'Deflatores Sisp'!G$42:H$70,2,FALSE))),VLOOKUP(C10,'Deflatores Sisp'!G$42:H$70,2,FALSE),IF(OR(ISBLANK(D10),ISBLANK(C10)),"",VLOOKUP(D10,'Deflatores Sisp'!G$4:H$38,2,FALSE)*K10+VLOOKUP(D10,'Deflatores Sisp'!G$4:I$38,3,FALSE)))*W10,"") -> 0.35 | T10: x | W10: =IF(V10="",SUM(Z10:AE10),IF(C10="PA",E10,100%)) -> 0.05 | Z10: =IF(P10="x",25%,0) -> 0 | AA10: =IF(Q10="x",10%,0) -> 0 | AB10: =IF(R10="x",40%,0) -> 0 | AC10: =IF(S10="x",15%,0) -> 0 | AD10: =IF(T10="x",5%,0) -> 0.05 | AE10: =IF(U10="x",5%,0) -> 0
B11: Perfis_e_Permissoes | C11: ALI | D11: I | E11: 14 | F11: TR 1 – Perfis (perfis) TD (8): id (uuid), nome (text), descricao (text), status (text), is_sistema (boolean), rota_padrao (text), created_at (timestamp), updated_at (timestamp). TR 2 – Permissões (permissoes) TD (6): id (uuid), codigo (text), nome (text), descricao (text), modulo (text), created_at (timestamp). TR 3 – Perfil-Permissões (perfil_permissoes) TD (3): perfil_id (uuid), permissao_id (uuid), created_at (timestamp). | G11: 3 | H11: (1) Perfis – grupos de permissões nomeados; (2) Permissões – permissões atômicas por módulo; (3) Perfil-Permissões – associação N:N entre perfis e permissões. | I11: =IF(ISBLANK(C11),"",IF(L11="L","Baixa",IF(L11="A","Média",IF(L11="","","Alta")))) -> Baixa | J11: =CONCATENATE(C11,L11) -> ALIL | K11: =IF(ISBLANK(C11),"",IF(C11="ALI",IF(L11="L",7,IF(L11="A",10,15)),IF(C11="AIE",IF(L11="L",5,IF(L11="A",7,10)),IF(C11="SE",IF(L11="L",4,IF(L11="A",5,7)),IF(OR(C11="EE",C11="CE"),IF(L11="L",3,IF(L11="A",4,6)),0))))) -> 7 | L11: =IF(OR(ISBLANK(E11),ISBLANK(G11)),IF(OR(C11="ALI",C11="AIE"),"L",IF(OR(C11="EE",C11="SE",C11="CE"),"A","")),IF(C11="EE",IF(G11>=3,IF(E11>=5,"H","A"),IF(G11>=2,IF(E11>=16,"H",IF(E11<=4,"L","A")),IF(E11<=15,"L","A"))),IF(OR(C11="SE",C11="CE"),IF(G11>=4,IF(E11>=6,"H","A"),IF(G11>=2,IF(E11>=20,"H",IF(E11<=5,"L","A")),IF(E11<=19,"L","A"))),IF(OR(C11="ALI",C11="AIE"),IF(G11>=6,IF(E11>=20,"H","A"),IF(G11>=2,IF(E11>=51,"H",IF(E11<=19,"L","A")),IF(E11<=50,"L","A"))),"")))) -> L | M11: =CONCATENATE(C11,D11) -> ALII | N11: =IF(OR(K11="",K11=0),O11,K11) -> 7 | O11: =IFERROR(IF(NOT(ISERROR(VLOOKUP(C11,'Deflatores Sisp'!G$42:H$70,2,FALSE))),VLOOKUP(C11,'Deflatores Sisp'!G$42:H$70,2,FALSE),IF(OR(ISBLANK(D11),ISBLANK(C11)),"",VLOOKUP(D11,'Deflatores Sisp'!G$4:H$38,2,FALSE)*K11+VLOOKUP(D11,'Deflatores Sisp'!G$4:I$38,3,FALSE)))*W11,"") -> 0.35 | T11: x | W11: =IF(V11="",SUM(Z11:AE11),IF(C11="PA",E11,100%)) -> 0.05 | Z11: =IF(P11="x",25%,0) -> 0 | AA11: =IF(Q11="x",10%,0) -> 0 | AB11: =IF(R11="x",40%,0) -> 0 | AC11: =IF(S11="x",15%,0) -> 0 | AD11: =IF(T11="x",5%,0) -> 0.05 | AE11: =IF(U11="x",5%,0) -> 0
B12: Tipos_Documentos | C12: ALI | D12: I | E12: 6 | F12: TR 1 – Tipos de Documentos (tipos_documentos) TD (6): id (uuid), nome (text), validade_em_dias (integer), status (text), created_at (timestamp), updated_at (timestamp). | G12: 1 | H12: (1) Tipos de Documentos – cadastro de tipos de documentos exigidos para adesão (RG, CPF, Contrato Social, etc.). | I12: =IF(ISBLANK(C12),"",IF(L12="L","Baixa",IF(L12="A","Média",IF(L12="","","Alta")))) -> Baixa | J12: =CONCATENATE(C12,L12) -> ALIL | K12: =IF(ISBLANK(C12),"",IF(C12="ALI",IF(L12="L",7,IF(L12="A",10,15)),IF(C12="AIE",IF(L12="L",5,IF(L12="A",7,10)),IF(C12="SE",IF(L12="L",4,IF(L12="A",5,7)),IF(OR(C12="EE",C12="CE"),IF(L12="L",3,IF(L12="A",4,6)),0))))) -> 7 | L12: =IF(OR(ISBLANK(E12),ISBLANK(G12)),IF(OR(C12="ALI",C12="AIE"),"L",IF(OR(C12="EE",C12="SE",C12="CE"),"A","")),IF(C12="EE",IF(G12>=3,IF(E12>=5,"H","A"),IF(G12>=2,IF(E12>=16,"H",IF(E12<=4,"L","A")),IF(E12<=15,"L","A"))),IF(OR(C12="SE",C12="CE"),IF(G12>=4,IF(E12>=6,"H","A"),IF(G12>=2,IF(E12>=20,"H",IF(E12<=5,"L","A")),IF(E12<=19,"L","A"))),IF(OR(C12="ALI",C12="AIE"),IF(G12>=6,IF(E12>=20,"H","A"),IF(G12>=2,IF(E12>=51,"H",IF(E12<=19,"L","A")),IF(E12<=50,"L","A"))),"")))) -> L | M12: =CONCATENATE(C12,D12) -> ALII | N12: =IF(OR(K12="",K12=0),O12,K12) -> 7 | O12: =IFERROR(IF(NOT(ISERROR(VLOOKUP(C12,'Deflatores Sisp'!G$42:H$70,2,FALSE))),VLOOKUP(C12,'Deflatores Sisp'!G$42:H$70,2,FALSE),IF(OR(ISBLANK(D12),ISBLANK(C12)),"",VLOOKUP(D12,'Deflatores Sisp'!G$4:H$38,2,FALSE)*K12+VLOOKUP(D12,'Deflatores Sisp'!G$4:I$38,3,FALSE)))*W12,"") -> 0.35 | T12: x | W12: =IF(V12="",SUM(Z12:AE12),IF(C12="PA",E12,100%)) -> 0.05 | Z12: =IF(P12="x",25%,0) -> 0 | AA12: =IF(Q12="x",10%,0) -> 0 | AB12: =IF(R12="x",40%,0) -> 0 | AC12: =IF(S12="x",15%,0) -> 0 | AD12: =IF(T12="x",5%,0) -> 0.05 | AE12: =IF(U12="x",5%,0) -> 0
B13: Sistemas_Origem_e_Docs | C13: ALI | D13: I | E13: 10 | F13: TR 1 – Sistemas de Origem (sistemas_origem) TD (8): id (uuid), nome (text), sigla (text), permite_cadastro_manual (boolean), exige_documentacao_complementar (boolean), status (text), created_at (timestamp), updated_at (timestamp). TR 2 – Documentos Obrigatórios (sistema_origem_documentos_obrigatorios) TD (2): sistema_origem_id (uuid), tipo_documento_id (uuid). | G13: 2 | H13: (1) Sistemas de Origem – sistemas externos que geram consumo (CNH SRV, CRV); (2) Documentos Obrigatórios – relação N:N definindo quais documentos são exigidos por sistema. | I13: =IF(ISBLANK(C13),"",IF(L13="L","Baixa",IF(L13="A","Média",IF(L13="","","Alta")))) -> Baixa | J13: =CONCATENATE(C13,L13) -> ALIL | K13: =IF(ISBLANK(C13),"",IF(C13="ALI",IF(L13="L",7,IF(L13="A",10,15)),IF(C13="AIE",IF(L13="L",5,IF(L13="A",7,10)),IF(C13="SE",IF(L13="L",4,IF(L13="A",5,7)),IF(OR(C13="EE",C13="CE"),IF(L13="L",3,IF(L13="A",4,6)),0))))) -> 7 | L13: =IF(OR(ISBLANK(E13),ISBLANK(G13)),IF(OR(C13="ALI",C13="AIE"),"L",IF(OR(C13="EE",C13="SE",C13="CE"),"A","")),IF(C13="EE",IF(G13>=3,IF(E13>=5,"H","A"),IF(G13>=2,IF(E13>=16,"H",IF(E13<=4,"L","A")),IF(E13<=15,"L","A"))),IF(OR(C13="SE",C13="CE"),IF(G13>=4,IF(E13>=6,"H","A"),IF(G13>=2,IF(E13>=20,"H",IF(E13<=5,"L","A")),IF(E13<=19,"L","A"))),IF(OR(C13="ALI",C13="AIE"),IF(G13>=6,IF(E13>=20,"H","A"),IF(G13>=2,IF(E13>=51,"H",IF(E13<=19,"L","A")),IF(E13<=50,"L","A"))),"")))) -> L | M13: =CONCATENATE(C13,D13) -> ALII | N13: =IF(OR(K13="",K13=0),O13,K13) -> 7 | O13: =IFERROR(IF(NOT(ISERROR(VLOOKUP(C13,'Deflatores Sisp'!G$42:H$70,2,FALSE))),VLOOKUP(C13,'Deflatores Sisp'!G$42:H$70,2,FALSE),IF(OR(ISBLANK(D13),ISBLANK(C13)),"",VLOOKUP(D13,'Deflatores Sisp'!G$4:H$38,2,FALSE)*K13+VLOOKUP(D13,'Deflatores Sisp'!G$4:I$38,3,FALSE)))*W13,"") -> 0.35 | T13: x | W13: =IF(V13="",SUM(Z13:AE13),IF(C13="PA",E13,100%)) -> 0.05 | Z13: =IF(P13="x",25%,0) -> 0 | AA13: =IF(Q13="x",10%,0) -> 0 | AB13: =IF(R13="x",40%,0) -> 0 | AC13: =IF(S13="x",15%,0) -> 0 | AD13: =IF(T13="x",5%,0) -> 0.05 | AE13: =IF(U13="x",5%,0) -> 0
B14: Modelos_Contrato | C14: ALI | D14: I | E14: 9 | F14: TR 1 – Modelos de Contrato (modelos_contrato) TD (9): id (uuid), codigo (text), nome (text), conteudo_modelo (text), data_vigencia_inicial (date), data_vigencia_final (date), status (text), created_at (timestamp), updated_at (timestamp). | G14: 1 | H14: (1) Modelos de Contrato – templates de contrato com merge fields para geração automática de contratos. | I14: =IF(ISBLANK(C14),"",IF(L14="L","Baixa",IF(L14="A","Média",IF(L14="","","Alta")))) -> Baixa | J14: =CONCATENATE(C14,L14) -> ALIL | K14: =IF(ISBLANK(C14),"",IF(C14="ALI",IF(L14="L",7,IF(L14="A",10,15)),IF(C14="AIE",IF(L14="L",5,IF(L14="A",7,10)),IF(C14="SE",IF(L14="L",4,IF(L14="A",5,7)),IF(OR(C14="EE",C14="CE"),IF(L14="L",3,IF(L14="A",4,6)),0))))) -> 7 | L14: =IF(OR(ISBLANK(E14),ISBLANK(G14)),IF(OR(C14="ALI",C14="AIE"),"L",IF(OR(C14="EE",C14="SE",C14="CE"),"A","")),IF(C14="EE",IF(G14>=3,IF(E14>=5,"H","A"),IF(G14>=2,IF(E14>=16,"H",IF(E14<=4,"L","A")),IF(E14<=15,"L","A"))),IF(OR(C14="SE",C14="CE"),IF(G14>=4,IF(E14>=6,"H","A"),IF(G14>=2,IF(E14>=20,"H",IF(E14<=5,"L","A")),IF(E14<=19,"L","A"))),IF(OR(C14="ALI",C14="AIE"),IF(G14>=6,IF(E14>=20,"H","A"),IF(G14>=2,IF(E14>=51,"H",IF(E14<=19,"L","A")),IF(E14<=50,"L","A"))),"")))) -> L | M14: =CONCATENATE(C14,D14) -> ALII | N14: =IF(OR(K14="",K14=0),O14,K14) -> 7 | O14: =IFERROR(IF(NOT(ISERROR(VLOOKUP(C14,'Deflatores Sisp'!G$42:H$70,2,FALSE))),VLOOKUP(C14,'Deflatores Sisp'!G$42:H$70,2,FALSE),IF(OR(ISBLANK(D14),ISBLANK(C14)),"",VLOOKUP(D14,'Deflatores Sisp'!G$4:H$38,2,FALSE)*K14+VLOOKUP(D14,'Deflatores Sisp'!G$4:I$38,3,FALSE)))*W14,"") -> 0.35 | T14: x | W14: =IF(V14="",SUM(Z14:AE14),IF(C14="PA",E14,100%)) -> 0.05 | Z14: =IF(P14="x",25%,0) -> 0 | AA14: =IF(Q14="x",10%,0) -> 0 | AB14: =IF(R14="x",40%,0) -> 0 | AC14: =IF(S14="x",15%,0) -> 0 | AD14: =IF(T14="x",5%,0) -> 0.05 | AE14: =IF(U14="x",5%,0) -> 0
B15: Propostas_e_Documentos | C15: ALI | D15: I | E15: 22 | F15: TR 1 – Propostas (propostas) TD (10): id (uuid), cliente_id (uuid), sistema_origem_id (uuid), modelo_contrato_id (uuid), data_proposta (timestamp), status (text), observacoes (text), created_by (uuid), created_at (timestamp), updated_at (timestamp). TR 2 – Documentos do Cliente (documentos_cliente) TD (12): id (uuid), proposta_id (uuid), tipo_documento_id (uuid), url_documento (text), numero_documento (text), data_upload (timestamp), status (text), motivo_recusa (text), aprovado_por (uuid), data_aprovacao (timestamp), created_at (timestamp), updated_at (timestamp). | G15: 2 | H15: (1) Propostas – registro de propostas comerciais vinculando cliente, sistema e modelo; (2) Documentos do Cliente – uploads de documentos com workflow de aprovação/recusa. | I15: =IF(ISBLANK(C15),"",IF(L15="L","Baixa",IF(L15="A","Média",IF(L15="","","Alta")))) -> Média | J15: =CONCATENATE(C15,L15) -> ALIA | K15: =IF(ISBLANK(C15),"",IF(C15="ALI",IF(L15="L",7,IF(L15="A",10,15)),IF(C15="AIE",IF(L15="L",5,IF(L15="A",7,10)),IF(C15="SE",IF(L15="L",4,IF(L15="A",5,7)),IF(OR(C15="EE",C15="CE"),IF(L15="L",3,IF(L15="A",4,6)),0))))) -> 10 | L15: =IF(OR(ISBLANK(E15),ISBLANK(G15)),IF(OR(C15="ALI",C15="AIE"),"L",IF(OR(C15="EE",C15="SE",C15="CE"),"A","")),IF(C15="EE",IF(G15>=3,IF(E15>=5,"H","A"),IF(G15>=2,IF(E15>=16,"H",IF(E15<=4,"L","A")),IF(E15<=15,"L","A"))),IF(OR(C15="SE",C15="CE"),IF(G15>=4,IF(E15>=6,"H","A"),IF(G15>=2,IF(E15>=20,"H",IF(E15<=5,"L","A")),IF(E15<=19,"L","A"))),IF(OR(C15="ALI",C15="AIE"),IF(G15>=6,IF(E15>=20,"H","A"),IF(G15>=2,IF(E15>=51,"H",IF(E15<=19,"L","A")),IF(E15<=50,"L","A"))),"")))) -> A | M15: =CONCATENATE(C15,D15) -> ALII | N15: =IF(OR(K15="",K15=0),O15,K15) -> 10 | O15: =IFERROR(IF(NOT(ISERROR(VLOOKUP(C15,'Deflatores Sisp'!G$42:H$70,2,FALSE))),VLOOKUP(C15,'Deflatores Sisp'!G$42:H$70,2,FALSE),IF(OR(ISBLANK(D15),ISBLANK(C15)),"",VLOOKUP(D15,'Deflatores Sisp'!G$4:H$38,2,FALSE)*K15+VLOOKUP(D15,'Deflatores Sisp'!G$4:I$38,3,FALSE)))*W15,"") -> 0.5 | T15: x | W15: =IF(V15="",SUM(Z15:AE15),IF(C15="PA",E15,100%)) -> 0.05 | Z15: =IF(P15="x",25%,0) -> 0 | AA15: =IF(Q15="x",10%,0) -> 0 | AB15: =IF(R15="x",40%,0) -> 0 | AC15: =IF(S15="x",15%,0) -> 0 | AD15: =IF(T15="x",5%,0) -> 0.05 | AE15: =IF(U15="x",5%,0) -> 0
B16: Contratos | C16: ALI | D16: I | E16: 12 | F16: TR 1 – Contratos (contratos) TD (12): id (uuid), proposta_id (uuid), cliente_id (uuid), sistema_origem_id (uuid), modelo_contrato_id (uuid), numero_contrato (text), data_assinatura (timestamp), status (text), motivo_suspensao (text), url_contrato_assinado (text), created_at (timestamp), updated_at (timestamp). | G16: 1 | H16: (1) Contratos – contratos assinados gerados a partir de propostas aprovadas, representando a unidade financeira do cliente. | I16: =IF(ISBLANK(C16),"",IF(L16="L","Baixa",IF(L16="A","Média",IF(L16="","","Alta")))) -> Baixa | J16: =CONCATENATE(C16,L16) -> ALIL | K16: =IF(ISBLANK(C16),"",IF(C16="ALI",IF(L16="L",7,IF(L16="A",10,15)),IF(C16="AIE",IF(L16="L",5,IF(L16="A",7,10)),IF(C16="SE",IF(L16="L",4,IF(L16="A",5,7)),IF(OR(C16="EE",C16="CE"),IF(L16="L",3,IF(L16="A",4,6)),0))))) -> 7 | L16: =IF(OR(ISBLANK(E16),ISBLANK(G16)),IF(OR(C16="ALI",C16="AIE"),"L",IF(OR(C16="EE",C16="SE",C16="CE"),"A","")),IF(C16="EE",IF(G16>=3,IF(E16>=5,"H","A"),IF(G16>=2,IF(E16>=16,"H",IF(E16<=4,"L","A")),IF(E16<=15,"L","A"))),IF(OR(C16="SE",C16="CE"),IF(G16>=4,IF(E16>=6,"H","A"),IF(G16>=2,IF(E16>=20,"H",IF(E16<=5,"L","A")),IF(E16<=19,"L","A"))),IF(OR(C16="ALI",C16="AIE"),IF(G16>=6,IF(E16>=20,"H","A"),IF(G16>=2,IF(E16>=51,"H",IF(E16<=19,"L","A")),IF(E16<=50,"L","A"))),"")))) -> L | M16: =CONCATENATE(C16,D16) -> ALII | N16: =IF(OR(K16="",K16=0),O16,K16) -> 7 | O16: =IFERROR(IF(NOT(ISERROR(VLOOKUP(C16,'Deflatores Sisp'!G$42:H$70,2,FALSE))),VLOOKUP(C16,'Deflatores Sisp'!G$42:H$70,2,FALSE),IF(OR(ISBLANK(D16),ISBLANK(C16)),"",VLOOKUP(D16,'Deflatores Sisp'!G$4:H$38,2,FALSE)*K16+VLOOKUP(D16,'Deflatores Sisp'!G$4:I$38,3,FALSE)))*W16,"") -> 0.35 | T16: x | W16: =IF(V16="",SUM(Z16:AE16),IF(C16="PA",E16,100%)) -> 0.05 | Z16: =IF(P16="x",25%,0) -> 0 | AA16: =IF(Q16="x",10%,0) -> 0 | AB16: =IF(R16="x",40%,0) -> 0 | AC16: =IF(S16="x",15%,0) -> 0 | AD16: =IF(T16="x",5%,0) -> 0.05 | AE16: =IF(U16="x",5%,0) -> 0
B17: Servicos_Faturaveis | C17: ALI | D17: I | E17: 12 | F17: TR 1 – Serviços Faturáveis (servicos_faturaveis) TD (12): id (uuid), codigo_prodesp (text), numero_transacao (text), descricao (text), valor (numeric), data_vigencia_inicial (date), data_vigencia_final (date), exibir_no_extrato (boolean), cobrar_por_hora_dia (boolean), status (text), created_at (timestamp), updated_at (timestamp). | G17: 1 | H17: (1) Serviços Faturáveis – catálogo de serviços cobráveis com valores e vigências. | I17: =IF(ISBLANK(C17),"",IF(L17="L","Baixa",IF(L17="A","Média",IF(L17="","","Alta")))) -> Baixa | J17: =CONCATENATE(C17,L17) -> ALIL | K17: =IF(ISBLANK(C17),"",IF(C17="ALI",IF(L17="L",7,IF(L17="A",10,15)),IF(C17="AIE",IF(L17="L",5,IF(L17="A",7,10)),IF(C17="SE",IF(L17="L",4,IF(L17="A",5,7)),IF(OR(C17="EE",C17="CE"),IF(L17="L",3,IF(L17="A",4,6)),0))))) -> 7 | L17: =IF(OR(ISBLANK(E17),ISBLANK(G17)),IF(OR(C17="ALI",C17="AIE"),"L",IF(OR(C17="EE",C17="SE",C17="CE"),"A","")),IF(C17="EE",IF(G17>=3,IF(E17>=5,"H","A"),IF(G17>=2,IF(E17>=16,"H",IF(E17<=4,"L","A")),IF(E17<=15,"L","A"))),IF(OR(C17="SE",C17="CE"),IF(G17>=4,IF(E17>=6,"H","A"),IF(G17>=2,IF(E17>=20,"H",IF(E17<=5,"L","A")),IF(E17<=19,"L","A"))),IF(OR(C17="ALI",C17="AIE"),IF(G17>=6,IF(E17>=20,"H","A"),IF(G17>=2,IF(E17>=51,"H",IF(E17<=19,"L","A")),IF(E17<=50,"L","A"))),"")))) -> L | M17: =CONCATENATE(C17,D17) -> ALII | N17: =IF(OR(K17="",K17=0),O17,K17) -> 7 | O17: =IFERROR(IF(NOT(ISERROR(VLOOKUP(C17,'Deflatores Sisp'!G$42:H$70,2,FALSE))),VLOOKUP(C17,'Deflatores Sisp'!G$42:H$70,2,FALSE),IF(OR(ISBLANK(D17),ISBLANK(C17)),"",VLOOKUP(D17,'Deflatores Sisp'!G$4:H$38,2,FALSE)*K17+VLOOKUP(D17,'Deflatores Sisp'!G$4:I$38,3,FALSE)))*W17,"") -> 0.35 | T17: x | W17: =IF(V17="",SUM(Z17:AE17),IF(C17="PA",E17,100%)) -> 0.05 | Z17: =IF(P17="x",25%,0) -> 0 | AA17: =IF(Q17="x",10%,0) -> 0 | AB17: =IF(R17="x",40%,0) -> 0 | AC17: =IF(S17="x",15%,0) -> 0 | AD17: =IF(T17="x",5%,0) -> 0.05 | AE17: =IF(U17="x",5%,0) -> 0
B18: Servicos_Especiais_e_Agendamentos | C18: ALI | D18: I | E18: 18 | F18: TR 1 – Serviços Especiais (servicos_especiais) TD (5): id (uuid), descricao (text), tipo (text), status (text), created_at (timestamp), updated_at (timestamp). TR 2 – Agendamentos (agendamentos_servicos_especiais) TD (13): id (uuid), servico_especial_id (uuid), cliente_id (uuid), tipo_cliente_alvo (text), data_agendamento (date), data_aplicacao (date), tipo_calculo (text), valor_percentual (numeric), valor_fixo (numeric), status (text), created_by (uuid), created_at (timestamp), updated_at (timestamp). | G18: 2 | H18: (1) Serviços Especiais – créditos e débitos especiais para ajustes; (2) Agendamentos – programação de aplicação de serviços especiais por cliente ou grupo. | I18: =IF(ISBLANK(C18),"",IF(L18="L","Baixa",IF(L18="A","Média",IF(L18="","","Alta")))) -> Baixa | J18: =CONCATENATE(C18,L18) -> ALIL | K18: =IF(ISBLANK(C18),"",IF(C18="ALI",IF(L18="L",7,IF(L18="A",10,15)),IF(C18="AIE",IF(L18="L",5,IF(L18="A",7,10)),IF(C18="SE",IF(L18="L",4,IF(L18="A",5,7)),IF(OR(C18="EE",C18="CE"),IF(L18="L",3,IF(L18="A",4,6)),0))))) -> 7 | L18: =IF(OR(ISBLANK(E18),ISBLANK(G18)),IF(OR(C18="ALI",C18="AIE"),"L",IF(OR(C18="EE",C18="SE",C18="CE"),"A","")),IF(C18="EE",IF(G18>=3,IF(E18>=5,"H","A"),IF(G18>=2,IF(E18>=16,"H",IF(E18<=4,"L","A")),IF(E18<=15,"L","A"))),IF(OR(C18="SE",C18="CE"),IF(G18>=4,IF(E18>=6,"H","A"),IF(G18>=2,IF(E18>=20,"H",IF(E18<=5,"L","A")),IF(E18<=19,"L","A"))),IF(OR(C18="ALI",C18="AIE"),IF(G18>=6,IF(E18>=20,"H","A"),IF(G18>=2,IF(E18>=51,"H",IF(E18<=19,"L","A")),IF(E18<=50,"L","A"))),"")))) -> L | M18: =CONCATENATE(C18,D18) -> ALII | N18: =IF(OR(K18="",K18=0),O18,K18) -> 7 | O18: =IFERROR(IF(NOT(ISERROR(VLOOKUP(C18,'Deflatores Sisp'!G$42:H$70,2,FALSE))),VLOOKUP(C18,'Deflatores Sisp'!G$42:H$70,2,FALSE),IF(OR(ISBLANK(D18),ISBLANK(C18)),"",VLOOKUP(D18,'Deflatores Sisp'!G$4:H$38,2,FALSE)*K18+VLOOKUP(D18,'Deflatores Sisp'!G$4:I$38,3,FALSE)))*W18,"") -> 0.35 | T18: x | W18: =IF(V18="",SUM(Z18:AE18),IF(C18="PA",E18,100%)) -> 0.05 | Z18: =IF(P18="x",25%,0) -> 0 | AA18: =IF(Q18="x",10%,0) -> 0 | AB18: =IF(R18="x",40%,0) -> 0 | AC18: =IF(S18="x",15%,0) -> 0 | AD18: =IF(T18="x",5%,0) -> 0.05 | AE18: =IF(U18="x",5%,0) -> 0
B19: Municipios_e_Feriados | C19: ALI | D19: I | E19: 14 | F19: TR 1 – Municípios (municipios) TD (7): id (uuid), nome (text), uf (text), codigo_ibge (integer), status (text), created_at (timestamp), updated_at (timestamp). TR 2 – Feriados Regionais (feriados_regionais) TD (7): id (uuid), municipio_id (uuid), data_feriado (date), descricao (text), status (text), created_at (timestamp), updated_at (timestamp). | G19: 2 | H19: (1) Municípios – cadastro de municípios brasileiros com código IBGE; (2) Feriados Regionais – feriados por município para cálculo de dias úteis. | I19: =IF(ISBLANK(C19),"",IF(L19="L","Baixa",IF(L19="A","Média",IF(L19="","","Alta")))) -> Baixa | J19: =CONCATENATE(C19,L19) -> ALIL | K19: =IF(ISBLANK(C19),"",IF(C19="ALI",IF(L19="L",7,IF(L19="A",10,15)),IF(C19="AIE",IF(L19="L",5,IF(L19="A",7,10)),IF(C19="SE",IF(L19="L",4,IF(L19="A",5,7)),IF(OR(C19="EE",C19="CE"),IF(L19="L",3,IF(L19="A",4,6)),0))))) -> 7 | L19: =IF(OR(ISBLANK(E19),ISBLANK(G19)),IF(OR(C19="ALI",C19="AIE"),"L",IF(OR(C19="EE",C19="SE",C19="CE"),"A","")),IF(C19="EE",IF(G19>=3,IF(E19>=5,"H","A"),IF(G19>=2,IF(E19>=16,"H",IF(E19<=4,"L","A")),IF(E19<=15,"L","A"))),IF(OR(C19="SE",C19="CE"),IF(G19>=4,IF(E19>=6,"H","A"),IF(G19>=2,IF(E19>=20,"H",IF(E19<=5,"L","A")),IF(E19<=19,"L","A"))),IF(OR(C19="ALI",C19="AIE"),IF(G19>=6,IF(E19>=20,"H","A"),IF(G19>=2,IF(E19>=51,"H",IF(E19<=19,"L","A")),IF(E19<=50,"L","A"))),"")))) -> L | M19: =CONCATENATE(C19,D19) -> ALII | N19: =IF(OR(K19="",K19=0),O19,K19) -> 7 | O19: =IFERROR(IF(NOT(ISERROR(VLOOKUP(C19,'Deflatores Sisp'!G$42:H$70,2,FALSE))),VLOOKUP(C19,'Deflatores Sisp'!G$42:H$70,2,FALSE),IF(OR(ISBLANK(D19),ISBLANK(C19)),"",VLOOKUP(D19,'Deflatores Sisp'!G$4:H$38,2,FALSE)*K19+VLOOKUP(D19,'Deflatores Sisp'!G$4:I$38,3,FALSE)))*W19,"") -> 0.35 | T19: x | W19: =IF(V19="",SUM(Z19:AE19),IF(C19="PA",E19,100%)) -> 0.05 | Z19: =IF(P19="x",25%,0) -> 0 | AA19: =IF(Q19="x",10%,0) -> 0 | AB19: =IF(R19="x",40%,0) -> 0 | AC19: =IF(S19="x",15%,0) -> 0 | AD19: =IF(T19="x",5%,0) -> 0.05 | AE19: =IF(U19="x",5%,0) -> 0
B20: Taxas_Juros | C20: ALI | D20: I | E20: 8 | F20: TR 1 – Taxas e Juros (taxas_juros) TD (8): id (uuid), percentual_multa (numeric), juros_mora_ao_dia (numeric), data_vigencia_inicial (date), data_vigencia_final (date), status (text), created_at (timestamp), updated_at (timestamp). | G20: 1 | H20: (1) Taxas e Juros – configuração de multa e juros de mora aplicáveis a cobranças em atraso. | I20: =IF(ISBLANK(C20),"",IF(L20="L","Baixa",IF(L20="A","Média",IF(L20="","","Alta")))) -> Baixa | J20: =CONCATENATE(C20,L20) -> ALIL | K20: =IF(ISBLANK(C20),"",IF(C20="ALI",IF(L20="L",7,IF(L20="A",10,15)),IF(C20="AIE",IF(L20="L",5,IF(L20="A",7,10)),IF(C20="SE",IF(L20="L",4,IF(L20="A",5,7)),IF(OR(C20="EE",C20="CE"),IF(L20="L",3,IF(L20="A",4,6)),0))))) -> 7 | L20: =IF(OR(ISBLANK(E20),ISBLANK(G20)),IF(OR(C20="ALI",C20="AIE"),"L",IF(OR(C20="EE",C20="SE",C20="CE"),"A","")),IF(C20="EE",IF(G20>=3,IF(E20>=5,"H","A"),IF(G20>=2,IF(E20>=16,"H",IF(E20<=4,"L","A")),IF(E20<=15,"L","A"))),IF(OR(C20="SE",C20="CE"),IF(G20>=4,IF(E20>=6,"H","A"),IF(G20>=2,IF(E20>=20,"H",IF(E20<=5,"L","A")),IF(E20<=19,"L","A"))),IF(OR(C20="ALI",C20="AIE"),IF(G20>=6,IF(E20>=20,"H","A"),IF(G20>=2,IF(E20>=51,"H",IF(E20<=19,"L","A")),IF(E20<=50,"L","A"))),"")))) -> L | M20: =CONCATENATE(C20,D20) -> ALII | N20: =IF(OR(K20="",K20=0),O20,K20) -> 7 | O20: =IFERROR(IF(NOT(ISERROR(VLOOKUP(C20,'Deflatores Sisp'!G$42:H$70,2,FALSE))),VLOOKUP(C20,'Deflatores Sisp'!G$42:H$70,2,FALSE),IF(OR(ISBLANK(D20),ISBLANK(C20)),"",VLOOKUP(D20,'Deflatores Sisp'!G$4:H$38,2,FALSE)*K20+VLOOKUP(D20,'Deflatores Sisp'!G$4:I$38,3,FALSE)))*W20,"") -> 0.35 | T20: x | W20: =IF(V20="",SUM(Z20:AE20),IF(C20="PA",E20,100%)) -> 0.05 | Z20: =IF(P20="x",25%,0) -> 0 | AA20: =IF(Q20="x",10%,0) -> 0 | AB20: =IF(R20="x",40%,0) -> 0 | AC20: =IF(S20="x",15%,0) -> 0 | AD20: =IF(T20="x",5%,0) -> 0.05 | AE20: =IF(U20="x",5%,0) -> 0
... B88: Download_PDF_Nota | C88: CE | D88: I | E88: 7 | F88: TD (7): numero_nota, data_emissao, status, valor, descricao, nome_razao_social, cpf_cnpj | G88: 3 | H88: RLR (3): notas_debito, cobrancas, clientes | I88: =IF(ISBLANK(C88),"",IF(L88="L","Baixa",IF(L88="A","Média",IF(L88="","","Alta")))) -> Média | J88: =CONCATENATE(C88,L88) -> CEA | K88: =IF(ISBLANK(C88),"",IF(C88="ALI",IF(L88="L",7,IF(L88="A",10,15)),IF(C88="AIE",IF(L88="L",5,IF(L88="A",7,10)),IF(C88="SE",IF(L88="L",4,IF(L88="A",5,7)),IF(OR(C88="EE",C88="CE"),IF(L88="L",3,IF(L88="A",4,6)),0))))) -> 4 | L88: =IF(OR(ISBLANK(E88),ISBLANK(G88)),IF(OR(C88="ALI",C88="AIE"),"L",IF(OR(C88="EE",C88="SE",C88="CE"),"A","")),IF(C88="EE",IF(G88>=3,IF(E88>=5,"H","A"),IF(G88>=2,IF(E88>=16,"H",IF(E88<=4,"L","A")),IF(E88<=15,"L","A"))),IF(OR(C88="SE",C88="CE"),IF(G88>=4,IF(E88>=6,"H","A"),IF(G88>=2,IF(E88>=20,"H",IF(E88<=5,"L","A")),IF(E88<=19,"L","A"))),IF(OR(C88="ALI",C88="AIE"),IF(G88>=6,IF(E88>=20,"H","A"),IF(G88>=2,IF(E88>=51,"H",IF(E88<=19,"L","A")),IF(E88<=50,"L","A"))),"")))) -> A | M88: =CONCATENATE(C88,D88) -> CEI | N88: =IF(OR(K88="",K88=0),O88,K88) -> 4 | O88: =IFERROR(IF(NOT(ISERROR(VLOOKUP(C88,'Deflatores Sisp'!G$42:H$70,2,FALSE))),VLOOKUP(C88,'Deflatores Sisp'!G$42:H$70,2,FALSE),IF(OR(ISBLANK(D88),ISBLANK(C88)),"",VLOOKUP(D88,'Deflatores Sisp'!G$4:H$38,2,FALSE)*K88+VLOOKUP(D88,'Deflatores Sisp'!G$4:I$38,3,FALSE)))*W88,"") -> 0.2 | T88: x | W88: =IF(V88="",SUM(Z88:AE88),IF(C88="PA",E88,100%)) -> 0.05 | Z88: =IF(P88="x",25%,0) -> 0 | AA88: =IF(Q88="x",10%,0) -> 0 | AB88: =IF(R88="x",40%,0) -> 0 | AC88: =IF(S88="x",15%,0) -> 0 | AD88: =IF(T88="x",5%,0) -> 0.05 | AE88: =IF(U88="x",5%,0) -> 0
A89: M04-ABR/2026 | B89: Bilhetagem Portal Credenciados | C89: ALI | D89: I | E89: 12 | F89: id, classificacao, mes_referencia, ident_portal_delegados, cpf_responsavel, numero_contrato, quantidade, codigo_servico, razao_social, cnpj, historico_requisicao_id, created_at | G89: 2 | H89: 1-Bilhetagem (registros transacionais), 2-Vínculo_Requisição (FK historico) | I89: =IF(ISBLANK(C89),"",IF(L89="L","Baixa",IF(L89="A","Média",IF(L89="","","Alta")))) -> Baixa | J89: =CONCATENATE(C89,L89) -> ALIL | K89: =IF(ISBLANK(C89),"",IF(C89="ALI",IF(L89="L",7,IF(L89="A",10,15)),IF(C89="AIE",IF(L89="L",5,IF(L89="A",7,10)),IF(C89="SE",IF(L89="L",4,IF(L89="A",5,7)),IF(OR(C89="EE",C89="CE"),IF(L89="L",3,IF(L89="A",4,6)),0))))) -> 7 | L89: =IF(OR(ISBLANK(E89),ISBLANK(G89)),IF(OR(C89="ALI",C89="AIE"),"L",IF(OR(C89="EE",C89="SE",C89="CE"),"A","")),IF(C89="EE",IF(G89>=3,IF(E89>=5,"H","A"),IF(G89>=2,IF(E89>=16,"H",IF(E89<=4,"L","A")),IF(E89<=15,"L","A"))),IF(OR(C89="SE",C89="CE"),IF(G89>=4,IF(E89>=6,"H","A"),IF(G89>=2,IF(E89>=20,"H",IF(E89<=5,"L","A")),IF(E89<=19,"L","A"))),IF(OR(C89="ALI",C89="AIE"),IF(G89>=6,IF(E89>=20,"H","A"),IF(G89>=2,IF(E89>=51,"H",IF(E89<=19,"L","A")),IF(E89<=50,"L","A"))),"")))) -> L | M89: =CONCATENATE(C89,D89) -> ALII | N89: =IF(OR(K89="",K89=0),O89,K89) -> 7 | O89: =IFERROR(IF(NOT(ISERROR(VLOOKUP(C89,'Deflatores Sisp'!G$42:H$70,2,FALSE))),VLOOKUP(C89,'Deflatores Sisp'!G$42:H$70,2,FALSE),IF(OR(ISBLANK(D89),ISBLANK(C89)),"",VLOOKUP(D89,'Deflatores Sisp'!G$4:H$38,2,FALSE)*K89+VLOOKUP(D89,'Deflatores Sisp'!G$4:I$38,3,FALSE)))*W89,"") -> 0.35 | T89: x | W89: =IF(V89="",SUM(Z89:AE89),IF(C89="PA",E89,100%)) -> 0.05 | Z89: =IF(P89="x",25%,0) -> 0 | AA89: =IF(Q89="x",10%,0) -> 0 | AB89: =IF(R89="x",40%,0) -> 0 | AC89: =IF(S89="x",15%,0) -> 0 | AD89: =IF(T89="x",5%,0) -> 0.05 | AE89: =IF(U89="x",5%,0) -> 0
A90: M04-ABR/2026 | B90: Histórico Requisições Credenciados | C90: ALI | D90: I | E90: 7 | F90: id, url_json, status, user_id, user_email, metadata, created_at | G90: 2 | H90: 1-Requisições (dados cabeçalho), 2-Metadados (JSONB) | I90: =IF(ISBLANK(C90),"",IF(L90="L","Baixa",IF(L90="A","Média",IF(L90="","","Alta")))) -> Baixa | J90: =CONCATENATE(C90,L90) -> ALIL | K90: =IF(ISBLANK(C90),"",IF(C90="ALI",IF(L90="L",7,IF(L90="A",10,15)),IF(C90="AIE",IF(L90="L",5,IF(L90="A",7,10)),IF(C90="SE",IF(L90="L",4,IF(L90="A",5,7)),IF(OR(C90="EE",C90="CE"),IF(L90="L",3,IF(L90="A",4,6)),0))))) -> 7 | L90: =IF(OR(ISBLANK(E90),ISBLANK(G90)),IF(OR(C90="ALI",C90="AIE"),"L",IF(OR(C90="EE",C90="SE",C90="CE"),"A","")),IF(C90="EE",IF(G90>=3,IF(E90>=5,"H","A"),IF(G90>=2,IF(E90>=16,"H",IF(E90<=4,"L","A")),IF(E90<=15,"L","A"))),IF(OR(C90="SE",C90="CE"),IF(G90>=4,IF(E90>=6,"H","A"),IF(G90>=2,IF(E90>=20,"H",IF(E90<=5,"L","A")),IF(E90<=19,"L","A"))),IF(OR(C90="ALI",C90="AIE"),IF(G90>=6,IF(E90>=20,"H","A"),IF(G90>=2,IF(E90>=51,"H",IF(E90<=19,"L","A")),IF(E90<=50,"L","A"))),"")))) -> L | M90: =CONCATENATE(C90,D90) -> ALII | N90: =IF(OR(K90="",K90=0),O90,K90) -> 7 | O90: =IFERROR(IF(NOT(ISERROR(VLOOKUP(C90,'Deflatores Sisp'!G$42:H$70,2,FALSE))),VLOOKUP(C90,'Deflatores Sisp'!G$42:H$70,2,FALSE),IF(OR(ISBLANK(D90),ISBLANK(C90)),"",VLOOKUP(D90,'Deflatores Sisp'!G$4:H$38,2,FALSE)*K90+VLOOKUP(D90,'Deflatores Sisp'!G$4:I$38,3,FALSE)))*W90,"") -> 0.35 | T90: x | W90: =IF(V90="",SUM(Z90:AE90),IF(C90="PA",E90,100%)) -> 0.05 | Z90: =IF(P90="x",25%,0) -> 0 | AA90: =IF(Q90="x",10%,0) -> 0 | AB90: =IF(R90="x",40%,0) -> 0 | AC90: =IF(S90="x",15%,0) -> 0 | AD90: =IF(T90="x",5%,0) -> 0.05 | AE90: =IF(U90="x",5%,0) -> 0
A91: M04-ABR/2026 | B91: Calendário Credenciados | C91: ALI | D91: I | E91: 9 | F91: id, ano, mes, dia, horario_corte, horario_limite, created_by, created_at, updated_at | G91: 2 | H91: 1-Calendário (datas/horários), 2-Controle_Auditoria | I91: =IF(ISBLANK(C91),"",IF(L91="L","Baixa",IF(L91="A","Média",IF(L91="","","Alta")))) -> Baixa | J91: =CONCATENATE(C91,L91) -> ALIL | K91: =IF(ISBLANK(C91),"",IF(C91="ALI",IF(L91="L",7,IF(L91="A",10,15)),IF(C91="AIE",IF(L91="L",5,IF(L91="A",7,10)),IF(C91="SE",IF(L91="L",4,IF(L91="A",5,7)),IF(OR(C91="EE",C91="CE"),IF(L91="L",3,IF(L91="A",4,6)),0))))) -> 7 | L91: =IF(OR(ISBLANK(E91),ISBLANK(G91)),IF(OR(C91="ALI",C91="AIE"),"L",IF(OR(C91="EE",C91="SE",C91="CE"),"A","")),IF(C91="EE",IF(G91>=3,IF(E91>=5,"H","A"),IF(G91>=2,IF(E91>=16,"H",IF(E91<=4,"L","A")),IF(E91<=15,"L","A"))),IF(OR(C91="SE",C91="CE"),IF(G91>=4,IF(E91>=6,"H","A"),IF(G91>=2,IF(E91>=20,"H",IF(E91<=5,"L","A")),IF(E91<=19,"L","A"))),IF(OR(C91="ALI",C91="AIE"),IF(G91>=6,IF(E91>=20,"H","A"),IF(G91>=2,IF(E91>=51,"H",IF(E91<=19,"L","A")),IF(E91<=50,"L","A"))),"")))) -> L | M91: =CONCATENATE(C91,D91) -> ALII | N91: =IF(OR(K91="",K91=0),O91,K91) -> 7 | O91: =IFERROR(IF(NOT(ISERROR(VLOOKUP(C91,'Deflatores Sisp'!G$42:H$70,2,FALSE))),VLOOKUP(C91,'Deflatores Sisp'!G$42:H$70,2,FALSE),IF(OR(ISBLANK(D91),ISBLANK(C91)),"",VLOOKUP(D91,'Deflatores Sisp'!G$4:H$38,2,FALSE)*K91+VLOOKUP(D91,'Deflatores Sisp'!G$4:I$38,3,FALSE)))*W91,"") -> 0.35 | T91: x | W91: =IF(V91="",SUM(Z91:AE91),IF(C91="PA",E91,100%)) -> 0.05 | Z91: =IF(P91="x",25%,0) -> 0 | AA91: =IF(Q91="x",10%,0) -> 0 | AB91: =IF(R91="x",40%,0) -> 0 | AC91: =IF(S91="x",15%,0) -> 0 | AD91: =IF(T91="x",5%,0) -> 0.05 | AE91: =IF(U91="x",5%,0) -> 0
A92: M04-ABR/2026 | B92: Execuções Consolidação Credenciados | C92: ALI | D92: I | E92: 16 | F92: id, mes_referencia, status, etapa, progresso, total_bilhetagem, total_grupos, total_inseridos, total_erros, valor_total, erros_detalhes, mensagem, iniciado_por, created_at, updated_at | G92: 4 | H92: 1-Execução (cabeçalho), 2-Progresso (etapa/percentual), 3-Totalizadores (grupos/erros/valor), 4-Detalhes_Erros (JSONB) | I92: =IF(ISBLANK(C92),"",IF(L92="L","Baixa",IF(L92="A","Média",IF(L92="","","Alta")))) -> Baixa | J92: =CONCATENATE(C92,L92) -> ALIL | K92: =IF(ISBLANK(C92),"",IF(C92="ALI",IF(L92="L",7,IF(L92="A",10,15)),IF(C92="AIE",IF(L92="L",5,IF(L92="A",7,10)),IF(C92="SE",IF(L92="L",4,IF(L92="A",5,7)),IF(OR(C92="EE",C92="CE"),IF(L92="L",3,IF(L92="A",4,6)),0))))) -> 7 | L92: =IF(OR(ISBLANK(E92),ISBLANK(G92)),IF(OR(C92="ALI",C92="AIE"),"L",IF(OR(C92="EE",C92="SE",C92="CE"),"A","")),IF(C92="EE",IF(G92>=3,IF(E92>=5,"H","A"),IF(G92>=2,IF(E92>=16,"H",IF(E92<=4,"L","A")),IF(E92<=15,"L","A"))),IF(OR(C92="SE",C92="CE"),IF(G92>=4,IF(E92>=6,"H","A"),IF(G92>=2,IF(E92>=20,"H",IF(E92<=5,"L","A")),IF(E92<=19,"L","A"))),IF(OR(C92="ALI",C92="AIE"),IF(G92>=6,IF(E92>=20,"H","A"),IF(G92>=2,IF(E92>=51,"H",IF(E92<=19,"L","A")),IF(E92<=50,"L","A"))),"")))) -> L | M92: =CONCATENATE(C92,D92) -> ALII | N92: =IF(OR(K92="",K92=0),O92,K92) -> 7 | O92: =IFERROR(IF(NOT(ISERROR(VLOOKUP(C92,'Deflatores Sisp'!G$42:H$70,2,FALSE))),VLOOKUP(C92,'Deflatores Sisp'!G$42:H$70,2,FALSE),IF(OR(ISBLANK(D92),ISBLANK(C92)),"",VLOOKUP(D92,'Deflatores Sisp'!G$4:H$38,2,FALSE)*K92+VLOOKUP(D92,'Deflatores Sisp'!G$4:I$38,3,FALSE)))*W92,"") -> 0.35 | T92: x | W92: =IF(V92="",SUM(Z92:AE92),IF(C92="PA",E92,100%)) -> 0.05 | Z92: =IF(P92="x",25%,0) -> 0 | AA92: =IF(Q92="x",10%,0) -> 0 | AB92: =IF(R92="x",40%,0) -> 0 | AC92: =IF(S92="x",15%,0) -> 0 | AD92: =IF(T92="x",5%,0) -> 0.05 | AE92: =IF(U92="x",5%,0) -> 0
A93: M04-ABR/2026 | B93: Configurações Integração DB (eCRV) | C93: ALI | D93: I | E93: 10 | F93: id, nome_integracao, host, port, username, password_encrypted, database_name, status, created_at, updated_at | G93: 2 | H93: 1-Conexão (host/port/user), 2-Credenciais (password criptografado) | I93: =IF(ISBLANK(C93),"",IF(L93="L","Baixa",IF(L93="A","Média",IF(L93="","","Alta")))) -> Baixa | J93: =CONCATENATE(C93,L93) -> ALIL | K93: =IF(ISBLANK(C93),"",IF(C93="ALI",IF(L93="L",7,IF(L93="A",10,15)),IF(C93="AIE",IF(L93="L",5,IF(L93="A",7,10)),IF(C93="SE",IF(L93="L",4,IF(L93="A",5,7)),IF(OR(C93="EE",C93="CE"),IF(L93="L",3,IF(L93="A",4,6)),0))))) -> 7 | L93: =IF(OR(ISBLANK(E93),ISBLANK(G93)),IF(OR(C93="ALI",C93="AIE"),"L",IF(OR(C93="EE",C93="SE",C93="CE"),"A","")),IF(C93="EE",IF(G93>=3,IF(E93>=5,"H","A"),IF(G93>=2,IF(E93>=16,"H",IF(E93<=4,"L","A")),IF(E93<=15,"L","A"))),IF(OR(C93="SE",C93="CE"),IF(G93>=4,IF(E93>=6,"H","A"),IF(G93>=2,IF(E93>=20,"H",IF(E93<=5,"L","A")),IF(E93<=19,"L","A"))),IF(OR(C93="ALI",C93="AIE"),IF(G93>=6,IF(E93>=20,"H","A"),IF(G93>=2,IF(E93>=51,"H",IF(E93<=19,"L","A")),IF(E93<=50,"L","A"))),"")))) -> L | M93: =CONCATENATE(C93,D93) -> ALII | N93: =IF(OR(K93="",K93=0),O93,K93) -> 7 | O93: =IFERROR(IF(NOT(ISERROR(VLOOKUP(C93,'Deflatores Sisp'!G$42:H$70,2,FALSE))),VLOOKUP(C93,'Deflatores Sisp'!G$42:H$70,2,FALSE),IF(OR(ISBLANK(D93),ISBLANK(C93)),"",VLOOKUP(D93,'Deflatores Sisp'!G$4:H$38,2,FALSE)*K93+VLOOKUP(D93,'Deflatores Sisp'!G$4:I$38,3,FALSE)))*W93,"") -> 0.35 | T93: x | W93: =IF(V93="",SUM(Z93:AE93),IF(C93="PA",E93,100%)) -> 0.05 | Z93: =IF(P93="x",25%,0) -> 0 | AA93: =IF(Q93="x",10%,0) -> 0 | AB93: =IF(R93="x",40%,0) -> 0 | AC93: =IF(S93="x",15%,0) -> 0 | AD93: =IF(T93="x",5%,0) -> 0.05 | AE93: =IF(U93="x",5%,0) -> 0
A94: M04-ABR/2026 | B94: Convites de Usuário | C94: ALI | D94: I | E94: 11 | F94: id, email, role, token, status, expires_at, created_by, created_at, updated_at, used_at, used_by | G94: 3 | H94: 1-Convite (dados), 2-Token (segurança), 3-Uso (rastreabilidade) | I94: =IF(ISBLANK(C94),"",IF(L94="L","Baixa",IF(L94="A","Média",IF(L94="","","Alta")))) -> Baixa | J94: =CONCATENATE(C94,L94) -> ALIL | K94: =IF(ISBLANK(C94),"",IF(C94="ALI",IF(L94="L",7,IF(L94="A",10,15)),IF(C94="AIE",IF(L94="L",5,IF(L94="A",7,10)),IF(C94="SE",IF(L94="L",4,IF(L94="A",5,7)),IF(OR(C94="EE",C94="CE"),IF(L94="L",3,IF(L94="A",4,6)),0))))) -> 7 | L94: =IF(OR(ISBLANK(E94),ISBLANK(G94)),IF(OR(C94="ALI",C94="AIE"),"L",IF(OR(C94="EE",C94="SE",C94="CE"),"A","")),IF(C94="EE",IF(G94>=3,IF(E94>=5,"H","A"),IF(G94>=2,IF(E94>=16,"H",IF(E94<=4,"L","A")),IF(E94<=15,"L","A"))),IF(OR(C94="SE",C94="CE"),IF(G94>=4,IF(E94>=6,"H","A"),IF(G94>=2,IF(E94>=20,"H",IF(E94<=5,"L","A")),IF(E94<=19,"L","A"))),IF(OR(C94="ALI",C94="AIE"),IF(G94>=6,IF(E94>=20,"H","A"),IF(G94>=2,IF(E94>=51,"H",IF(E94<=19,"L","A")),IF(E94<=50,"L","A"))),"")))) -> L | M94: =CONCATENATE(C94,D94) -> ALII | N94: =IF(OR(K94="",K94=0),O94,K94) -> 7 | O94: =IFERROR(IF(NOT(ISERROR(VLOOKUP(C94,'Deflatores Sisp'!G$42:H$70,2,FALSE))),VLOOKUP(C94,'Deflatores Sisp'!G$42:H$70,2,FALSE),IF(OR(ISBLANK(D94),ISBLANK(C94)),"",VLOOKUP(D94,'Deflatores Sisp'!G$4:H$38,2,FALSE)*K94+VLOOKUP(D94,'Deflatores Sisp'!G$4:I$38,3,FALSE)))*W94,"") -> 0.35 | T94: x | W94: =IF(V94="",SUM(Z94:AE94),IF(C94="PA",E94,100%)) -> 0.05 | Z94: =IF(P94="x",25%,0) -> 0 | AA94: =IF(Q94="x",10%,0) -> 0 | AB94: =IF(R94="x",40%,0) -> 0 | AC94: =IF(S94="x",15%,0) -> 0 | AD94: =IF(T94="x",5%,0) -> 0.05 | AE94: =IF(U94="x",5%,0) -> 0
A95: M04-ABR/2026 | B95: Notas de Débito (Poupatempo) | C95: ALI | D95: I | E95: 14 | F95: id, contrato_id, cliente_nome, cpf_cnpj, mes_referencia, valor_total, quantidade_transacoes, data_emissao, data_vencimento, status, numero_nota, observacoes, created_at, updated_at | G95: 3 | H95: 1-Nota (cabeçalho), 2-Valores (cálculo), 3-Status_Controle | I95: =IF(ISBLANK(C95),"",IF(L95="L","Baixa",IF(L95="A","Média",IF(L95="","","Alta")))) -> Baixa | J95: =CONCATENATE(C95,L95) -> ALIL | K95: =IF(ISBLANK(C95),"",IF(C95="ALI",IF(L95="L",7,IF(L95="A",10,15)),IF(C95="AIE",IF(L95="L",5,IF(L95="A",7,10)),IF(C95="SE",IF(L95="L",4,IF(L95="A",5,7)),IF(OR(C95="EE",C95="CE"),IF(L95="L",3,IF(L95="A",4,6)),0))))) -> 7 | L95: =IF(OR(ISBLANK(E95),ISBLANK(G95)),IF(OR(C95="ALI",C95="AIE"),"L",IF(OR(C95="EE",C95="SE",C95="CE"),"A","")),IF(C95="EE",IF(G95>=3,IF(E95>=5,"H","A"),IF(G95>=2,IF(E95>=16,"H",IF(E95<=4,"L","A")),IF(E95<=15,"L","A"))),IF(OR(C95="SE",C95="CE"),IF(G95>=4,IF(E95>=6,"H","A"),IF(G95>=2,IF(E95>=20,"H",IF(E95<=5,"L","A")),IF(E95<=19,"L","A"))),IF(OR(C95="ALI",C95="AIE"),IF(G95>=6,IF(E95>=20,"H","A"),IF(G95>=2,IF(E95>=51,"H",IF(E95<=19,"L","A")),IF(E95<=50,"L","A"))),"")))) -> L | M95: =CONCATENATE(C95,D95) -> ALII | N95: =IF(OR(K95="",K95=0),O95,K95) -> 7 | O95: =IFERROR(IF(NOT(ISERROR(VLOOKUP(C95,'Deflatores Sisp'!G$42:H$70,2,FALSE))),VLOOKUP(C95,'Deflatores Sisp'!G$42:H$70,2,FALSE),IF(OR(ISBLANK(D95),ISBLANK(C95)),"",VLOOKUP(D95,'Deflatores Sisp'!G$4:H$38,2,FALSE)*K95+VLOOKUP(D95,'Deflatores Sisp'!G$4:I$38,3,FALSE)))*W95,"") -> 0.35 | T95: x | W95: =IF(V95="",SUM(Z95:AE95),IF(C95="PA",E95,100%)) -> 0.05 | Z95: =IF(P95="x",25%,0) -> 0 | AA95: =IF(Q95="x",10%,0) -> 0 | AB95: =IF(R95="x",40%,0) -> 0 | AC95: =IF(S95="x",15%,0) -> 0 | AD95: =IF(T95="x",5%,0) -> 0.05 | AE95: =IF(U95="x",5%,0) -> 0
A96: M04-ABR/2026 | B96: Informes Anuais Pagamento (Poupatempo) | C96: ALI | D96: I | E96: 12 | F96: id, ano_referencia, cliente_id, cpf_cnpj, nome_cliente, valor_total_ano, total_transacoes, data_geracao, status, url_arquivo, created_at, updated_at | G96: 2 | H96: 1-Informe (dados consolidados anuais), 2-Arquivo (geração PDF) | I96: =IF(ISBLANK(C96),"",IF(L96="L","Baixa",IF(L96="A","Média",IF(L96="","","Alta")))) -> Baixa | J96: =CONCATENATE(C96,L96) -> ALIL | K96: =IF(ISBLANK(C96),"",IF(C96="ALI",IF(L96="L",7,IF(L96="A",10,15)),IF(C96="AIE",IF(L96="L",5,IF(L96="A",7,10)),IF(C96="SE",IF(L96="L",4,IF(L96="A",5,7)),IF(OR(C96="EE",C96="CE"),IF(L96="L",3,IF(L96="A",4,6)),0))))) -> 7 | L96: =IF(OR(ISBLANK(E96),ISBLANK(G96)),IF(OR(C96="ALI",C96="AIE"),"L",IF(OR(C96="EE",C96="SE",C96="CE"),"A","")),IF(C96="EE",IF(G96>=3,IF(E96>=5,"H","A"),IF(G96>=2,IF(E96>=16,"H",IF(E96<=4,"L","A")),IF(E96<=15,"L","A"))),IF(OR(C96="SE",C96="CE"),IF(G96>=4,IF(E96>=6,"H","A"),IF(G96>=2,IF(E96>=20,"H",IF(E96<=5,"L","A")),IF(E96<=19,"L","A"))),IF(OR(C96="ALI",C96="AIE"),IF(G96>=6,IF(E96>=20,"H","A"),IF(G96>=2,IF(E96>=51,"H",IF(E96<=19,"L","A")),IF(E96<=50,"L","A"))),"")))) -> L | M96: =CONCATENATE(C96,D96) -> ALII | N96: =IF(OR(K96="",K96=0),O96,K96) -> 7 | O96: =IFERROR(IF(NOT(ISERROR(VLOOKUP(C96,'Deflatores Sisp'!G$42:H$70,2,FALSE))),VLOOKUP(C96,'Deflatores Sisp'!G$42:H$70,2,FALSE),IF(OR(ISBLANK(D96),ISBLANK(C96)),"",VLOOKUP(D96,'Deflatores Sisp'!G$4:H$38,2,FALSE)*K96+VLOOKUP(D96,'Deflatores Sisp'!G$4:I$38,3,FALSE)))*W96,"") -> 0.35 | T96: x | W96: =IF(V96="",SUM(Z96:AE96),IF(C96="PA",E96,100%)) -> 0.05 | Z96: =IF(P96="x",25%,0) -> 0 | AA96: =IF(Q96="x",10%,0) -> 0 | AB96: =IF(R96="x",40%,0) -> 0 | AC96: =IF(S96="x",15%,0) -> 0 | AD96: =IF(T96="x",5%,0) -> 0.05 | AE96: =IF(U96="x",5%,0) -> 0
A97: M04-ABR/2026 | B97: Pré-Faturamento Itens | C97: ALI | D97: I | E97: 18 | F97: id, periodo_id, contrato_id, cliente_id, sistema_origem_id, servico_id, quantidade, valor_unitario, valor_total, valor_desconto, valor_liquido, status, data_referencia, observacao, aprovado_por, data_aprovacao, created_at, updated_at | G97: 5 | H97: 1-Item (dados base), 2-Valores (cálculo), 3-Desconto (gratuidade), 4-Aprovação (workflow), 5-Vínculo_Período | I97: =IF(ISBLANK(C97),"",IF(L97="L","Baixa",IF(L97="A","Média",IF(L97="","","Alta")))) -> Baixa | J97: =CONCATENATE(C97,L97) -> ALIL | K97: =IF(ISBLANK(C97),"",IF(C97="ALI",IF(L97="L",7,IF(L97="A",10,15)),IF(C97="AIE",IF(L97="L",5,IF(L97="A",7,10)),IF(C97="SE",IF(L97="L",4,IF(L97="A",5,7)),IF(OR(C97="EE",C97="CE"),IF(L97="L",3,IF(L97="A",4,6)),0))))) -> 7 | L97: =IF(OR(ISBLANK(E97),ISBLANK(G97)),IF(OR(C97="ALI",C97="AIE"),"L",IF(OR(C97="EE",C97="SE",C97="CE"),"A","")),IF(C97="EE",IF(G97>=3,IF(E97>=5,"H","A"),IF(G97>=2,IF(E97>=16,"H",IF(E97<=4,"L","A")),IF(E97<=15,"L","A"))),IF(OR(C97="SE",C97="CE"),IF(G97>=4,IF(E97>=6,"H","A"),IF(G97>=2,IF(E97>=20,"H",IF(E97<=5,"L","A")),IF(E97<=19,"L","A"))),IF(OR(C97="ALI",C97="AIE"),IF(G97>=6,IF(E97>=20,"H","A"),IF(G97>=2,IF(E97>=51,"H",IF(E97<=19,"L","A")),IF(E97<=50,"L","A"))),"")))) -> L | M97: =CONCATENATE(C97,D97) -> ALII | N97: =IF(OR(K97="",K97=0),O97,K97) -> 7 | O97: =IFERROR(IF(NOT(ISERROR(VLOOKUP(C97,'Deflatores Sisp'!G$42:H$70,2,FALSE))),VLOOKUP(C97,'Deflatores Sisp'!G$42:H$70,2,FALSE),IF(OR(ISBLANK(D97),ISBLANK(C97)),"",VLOOKUP(D97,'Deflatores Sisp'!G$4:H$38,2,FALSE)*K97+VLOOKUP(D97,'Deflatores Sisp'!G$4:I$38,3,FALSE)))*W97,"") -> 0.35 | T97: x | W97: =IF(V97="",SUM(Z97:AE97),IF(C97="PA",E97,100%)) -> 0.05 | Z97: =IF(P97="x",25%,0) -> 0 | AA97: =IF(Q97="x",10%,0) -> 0 | AB97: =IF(R97="x",40%,0) -> 0 | AC97: =IF(S97="x",15%,0) -> 0 | AD97: =IF(T97="x",5%,0) -> 0.05 | AE97: =IF(U97="x",5%,0) -> 0
A98: M04-ABR/2026 | B98: Portal de Delegados — JSON Externo (Credenciados) | C98: AIE | D98: I | E98: 10 | F98: url_json, classificacao, mes_referencia, ident_portal_delegados, cpf_responsavel, numero_contrato, quantidade, codigo_servico, razao_social, cnpj | G98: 2 | H98: 1-Dados_Bilhetagem (campos transacionais), 2-Identificação_Credenciado | I98: =IF(ISBLANK(C98),"",IF(L98="L","Baixa",IF(L98="A","Média",IF(L98="","","Alta")))) -> Baixa | J98: =CONCATENATE(C98,L98) -> AIEL | K98: =IF(ISBLANK(C98),"",IF(C98="ALI",IF(L98="L",7,IF(L98="A",10,15)),IF(C98="AIE",IF(L98="L",5,IF(L98="A",7,10)),IF(C98="SE",IF(L98="L",4,IF(L98="A",5,7)),IF(OR(C98="EE",C98="CE"),IF(L98="L",3,IF(L98="A",4,6)),0))))) -> 5 | L98: =IF(OR(ISBLANK(E98),ISBLANK(G98)),IF(OR(C98="ALI",C98="AIE"),"L",IF(OR(C98="EE",C98="SE",C98="CE"),"A","")),IF(C98="EE",IF(G98>=3,IF(E98>=5,"H","A"),IF(G98>=2,IF(E98>=16,"H",IF(E98<=4,"L","A")),IF(E98<=15,"L","A"))),IF(OR(C98="SE",C98="CE"),IF(G98>=4,IF(E98>=6,"H","A"),IF(G98>=2,IF(E98>=20,"H",IF(E98<=5,"L","A")),IF(E98<=19,"L","A"))),IF(OR(C98="ALI",C98="AIE"),IF(G98>=6,IF(E98>=20,"H","A"),IF(G98>=2,IF(E98>=51,"H",IF(E98<=19,"L","A")),IF(E98<=50,"L","A"))),"")))) -> L | M98: =CONCATENATE(C98,D98) -> AIEI | N98: =IF(OR(K98="",K98=0),O98,K98) -> 5 | O98: =IFERROR(IF(NOT(ISERROR(VLOOKUP(C98,'Deflatores Sisp'!G$42:H$70,2,FALSE))),VLOOKUP(C98,'Deflatores Sisp'!G$42:H$70,2,FALSE),IF(OR(ISBLANK(D98),ISBLANK(C98)),"",VLOOKUP(D98,'Deflatores Sisp'!G$4:H$38,2,FALSE)*K98+VLOOKUP(D98,'Deflatores Sisp'!G$4:I$38,3,FALSE)))*W98,"") -> 0.25 | T98: x | W98: =IF(V98="",SUM(Z98:AE98),IF(C98="PA",E98,100%)) -> 0.05 | Z98: =IF(P98="x",25%,0) -> 0 | AA98: =IF(Q98="x",10%,0) -> 0 | AB98: =IF(R98="x",40%,0) -> 0 | AC98: =IF(S98="x",15%,0) -> 0 | AD98: =IF(T98="x",5%,0) -> 0.05 | AE98: =IF(U98="x",5%,0) -> 0
A99: M04-ABR/2026 | B99: ViaCEP (Consulta de Endereço) | C99: AIE | D99: I | E99: 8 | F99: cep, logradouro, complemento, bairro, localidade, uf, ibge, estado | G99: 1 | H99: 1-Endereço (dados de retorno) | I99: =IF(ISBLANK(C99),"",IF(L99="L","Baixa",IF(L99="A","Média",IF(L99="","","Alta")))) -> Baixa | J99: =CONCATENATE(C99,L99) -> AIEL | K99: =IF(ISBLANK(C99),"",IF(C99="ALI",IF(L99="L",7,IF(L99="A",10,15)),IF(C99="AIE",IF(L99="L",5,IF(L99="A",7,10)),IF(C99="SE",IF(L99="L",4,IF(L99="A",5,7)),IF(OR(C99="EE",C99="CE"),IF(L99="L",3,IF(L99="A",4,6)),0))))) -> 5 | L99: =IF(OR(ISBLANK(E99),ISBLANK(G99)),IF(OR(C99="ALI",C99="AIE"),"L",IF(OR(C99="EE",C99="SE",C99="CE"),"A","")),IF(C99="EE",IF(G99>=3,IF(E99>=5,"H","A"),IF(G99>=2,IF(E99>=16,"H",IF(E99<=4,"L","A")),IF(E99<=15,"L","A"))),IF(OR(C99="SE",C99="CE"),IF(G99>=4,IF(E99>=6,"H","A"),IF(G99>=2,IF(E99>=20,"H",IF(E99<=5,"L","A")),IF(E99<=19,"L","A"))),IF(OR(C99="ALI",C99="AIE"),IF(G99>=6,IF(E99>=20,"H","A"),IF(G99>=2,IF(E99>=51,"H",IF(E99<=19,"L","A")),IF(E99<=50,"L","A"))),"")))) -> L | M99: =CONCATENATE(C99,D99) -> AIEI | N99: =IF(OR(K99="",K99=0),O99,K99) -> 5 | O99: =IFERROR(IF(NOT(ISERROR(VLOOKUP(C99,'Deflatores Sisp'!G$42:H$70,2,FALSE))),VLOOKUP(C99,'Deflatores Sisp'!G$42:H$70,2,FALSE),IF(OR(ISBLANK(D99),ISBLANK(C99)),"",VLOOKUP(D99,'Deflatores Sisp'!G$4:H$38,2,FALSE)*K99+VLOOKUP(D99,'Deflatores Sisp'!G$4:I$38,3,FALSE)))*W99,"") -> 0.25 | T99: x | W99: =IF(V99="",SUM(Z99:AE99),IF(C99="PA",E99,100%)) -> 0.05 | Z99: =IF(P99="x",25%,0) -> 0 | AA99: =IF(Q99="x",10%,0) -> 0 | AB99: =IF(R99="x",40%,0) -> 0 | AC99: =IF(S99="x",15%,0) -> 0 | AD99: =IF(T99="x",5%,0) -> 0.05 | AE99: =IF(U99="x",5%,0) -> 0
A100: M04-ABR/2026 | B100: API ERP PRODESP (Sincronização de Clientes) | C100: AIE | D100: I | E100: 25 | F100: razaoSocial, numCpfCnpj, codTipoCliente, desNomeFantasia, numInscEstadual, codIbge, desEndereco, numEndereco, desComplemento, desBairro, numCep, desMunicipio, codUf, numTelefone, desEmail, codFlagIssRetido, codFlagIrrf, codFlagCpcRetido, desAtivEconomica, numCcm, numRgRne, desNacionalidade, codFlagGratuidade, codContribuinteIcms, codRegimeEspecial | G100: 4 | H100: 1-Dados_Empresa, 2-Endereço, 3-Contato, 4-Flags_Fiscais | I100: =IF(ISBLANK(C100),"",IF(L100="L","Baixa",IF(L100="A","Média",IF(L100="","","Alta")))) -> Média | J100: =CONCATENATE(C100,L100) -> AIEA | K100: =IF(ISBLANK(C100),"",IF(C100="ALI",IF(L100="L",7,IF(L100="A",10,15)),IF(C100="AIE",IF(L100="L",5,IF(L100="A",7,10)),IF(C100="SE",IF(L100="L",4,IF(L100="A",5,7)),IF(OR(C100="EE",C100="CE"),IF(L100="L",3,IF(L100="A",4,6)),0))))) -> 7 | L100: =IF(OR(ISBLANK(E100),ISBLANK(G100)),IF(OR(C100="ALI",C100="AIE"),"L",IF(OR(C100="EE",C100="SE",C100="CE"),"A","")),IF(C100="EE",IF(G100>=3,IF(E100>=5,"H","A"),IF(G100>=2,IF(E100>=16,"H",IF(E100<=4,"L","A")),IF(E100<=15,"L","A"))),IF(OR(C100="SE",C100="CE"),IF(G100>=4,IF(E100>=6,"H","A"),IF(G100>=2,IF(E100>=20,"H",IF(E100<=5,"L","A")),IF(E100<=19,"L","A"))),IF(OR(C100="ALI",C100="AIE"),IF(G100>=6,IF(E100>=20,"H","A"),IF(G100>=2,IF(E100>=51,"H",IF(E100<=19,"L","A")),IF(E100<=50,"L","A"))),"")))) -> A | M100: =CONCATENATE(C100,D100) -> AIEI | N100: =IF(OR(K100="",K100=0),O100,K100) -> 7 | O100: =IFERROR(IF(NOT(ISERROR(VLOOKUP(C100,'Deflatores Sisp'!G$42:H$70,2,FALSE))),VLOOKUP(C100,'Deflatores Sisp'!G$42:H$70,2,FALSE),IF(OR(ISBLANK(D100),ISBLANK(C100)),"",VLOOKUP(D100,'Deflatores Sisp'!G$4:H$38,2,FALSE)*K100+VLOOKUP(D100,'Deflatores Sisp'!G$4:I$38,3,FALSE)))*W100,"") -> 0.35 | T100: x | W100: =IF(V100="",SUM(Z100:AE100),IF(C100="PA",E100,100%)) -> 0.05 | Z100: =IF(P100="x",25%,0) -> 0 | AA100: =IF(Q100="x",10%,0) -> 0 | AB100: =IF(R100="x",40%,0) -> 0 | AC100: =IF(S100="x",15%,0) -> 0 | AD100: =IF(T100="x",5%,0) -> 0.05 | AE100: =IF(U100="x",5%,0) -> 0
... A162: M04-ABR/2026 | B162: Consulta Inadimplência (Financeiro) | C162: CE | D162: I | E162: 12 | F162: filtro_dias_atraso, filtro_sistema + resultado: cliente, cpf_cnpj, contrato, valor_original, data_vencimento, dias_atraso, valor_juros, valor_multa, valor_total | G162: 3 | H162: 1-cobrancas, 2-contratos, 3-clientes | I162: =IF(ISBLANK(C162),"",IF(L162="L","Baixa",IF(L162="A","Média",IF(L162="","","Alta")))) -> Média | J162: =CONCATENATE(C162,L162) -> CEA | K162: =IF(ISBLANK(C162),"",IF(C162="ALI",IF(L162="L",7,IF(L162="A",10,15)),IF(C162="AIE",IF(L162="L",5,IF(L162="A",7,10)),IF(C162="SE",IF(L162="L",4,IF(L162="A",5,7)),IF(OR(C162="EE",C162="CE"),IF(L162="L",3,IF(L162="A",4,6)),0))))) -> 4 | L162: =IF(OR(ISBLANK(E162),ISBLANK(G162)),IF(OR(C162="ALI",C162="AIE"),"L",IF(OR(C162="EE",C162="SE",C162="CE"),"A","")),IF(C162="EE",IF(G162>=3,IF(E162>=5,"H","A"),IF(G162>=2,IF(E162>=16,"H",IF(E162<=4,"L","A")),IF(E162<=15,"L","A"))),IF(OR(C162="SE",C162="CE"),IF(G162>=4,IF(E162>=6,"H","A"),IF(G162>=2,IF(E162>=20,"H",IF(E162<=5,"L","A")),IF(E162<=19,"L","A"))),IF(OR(C162="ALI",C162="AIE"),IF(G162>=6,IF(E162>=20,"H","A"),IF(G162>=2,IF(E162>=51,"H",IF(E162<=19,"L","A")),IF(E162<=50,"L","A"))),"")))) -> A | M162: =CONCATENATE(C162,D162) -> CEI | N162: =IF(OR(K162="",K162=0),O162,K162) -> 4 | O162: =IFERROR(IF(NOT(ISERROR(VLOOKUP(C162,'Deflatores Sisp'!G$42:H$70,2,FALSE))),VLOOKUP(C162,'Deflatores Sisp'!G$42:H$70,2,FALSE),IF(OR(ISBLANK(D162),ISBLANK(C162)),"",VLOOKUP(D162,'Deflatores Sisp'!G$4:H$38,2,FALSE)*K162+VLOOKUP(D162,'Deflatores Sisp'!G$4:I$38,3,FALSE)))*W162,"") -> 0.2 | T162: x | W162: =IF(V162="",SUM(Z162:AE162),IF(C162="PA",E162,100%)) -> 0.05 | Z162: =IF(P162="x",25%,0) -> 0 | AA162: =IF(Q162="x",10%,0) -> 0 | AB162: =IF(R162="x",40%,0) -> 0 | AC162: =IF(S162="x",15%,0) -> 0 | AD162: =IF(T162="x",5%,0) -> 0.05 | AE162: =IF(U162="x",5%,0) -> 0
A163: M04-ABR/2026 | B163: Tabela assinaturas_govbr | C163: ALI | D163: I | E163: 9 | F163: contrato_id, govbr_cpf, nome, sub, hash_documento, ip, user_agent, assinado_em, user_id | G163: 2 | H163: assinaturas_govbr + contratos | I163: =IF(ISBLANK(C163),"",IF(L163="L","Baixa",IF(L163="A","Média",IF(L163="","","Alta")))) -> Baixa | J163: =CONCATENATE(C163,L163) -> ALIL | K163: =IF(ISBLANK(C163),"",IF(C163="ALI",IF(L163="L",7,IF(L163="A",10,15)),IF(C163="AIE",IF(L163="L",5,IF(L163="A",7,10)),IF(C163="SE",IF(L163="L",4,IF(L163="A",5,7)),IF(OR(C163="EE",C163="CE"),IF(L163="L",3,IF(L163="A",4,6)),0))))) -> 7 | L163: =IF(OR(ISBLANK(E163),ISBLANK(G163)),IF(OR(C163="ALI",C163="AIE"),"L",IF(OR(C163="EE",C163="SE",C163="CE"),"A","")),IF(C163="EE",IF(G163>=3,IF(E163>=5,"H","A"),IF(G163>=2,IF(E163>=16,"H",IF(E163<=4,"L","A")),IF(E163<=15,"L","A"))),IF(OR(C163="SE",C163="CE"),IF(G163>=4,IF(E163>=6,"H","A"),IF(G163>=2,IF(E163>=20,"H",IF(E163<=5,"L","A")),IF(E163<=19,"L","A"))),IF(OR(C163="ALI",C163="AIE"),IF(G163>=6,IF(E163>=20,"H","A"),IF(G163>=2,IF(E163>=51,"H",IF(E163<=19,"L","A")),IF(E163<=50,"L","A"))),"")))) -> L | M163: =CONCATENATE(C163,D163) -> ALII | N163: =IF(OR(K163="",K163=0),O163,K163) -> 7 | O163: =IFERROR(IF(NOT(ISERROR(VLOOKUP(C163,'Deflatores Sisp'!G$42:H$70,2,FALSE))),VLOOKUP(C163,'Deflatores Sisp'!G$42:H$70,2,FALSE),IF(OR(ISBLANK(D163),ISBLANK(C163)),"",VLOOKUP(D163,'Deflatores Sisp'!G$4:H$38,2,FALSE)*K163+VLOOKUP(D163,'Deflatores Sisp'!G$4:I$38,3,FALSE)))*W163,"") -> 6.65 | P163: x | Q163: x | R163: x | S163: x | T163: x | W163: =IF(V163="",SUM(Z163:AE163),IF(C163="PA",E163,100%)) -> 0.95 | Z163: =IF(P163="x",25%,0) -> 0.25 | AA163: =IF(Q163="x",10%,0) -> 0.1 | AB163: =IF(R163="x",40%,0) -> 0.4 | AC163: =IF(S163="x",15%,0) -> 0.15 | AD163: =IF(T163="x",5%,0) -> 0.05 | AE163: =IF(U163="x",5%,0) -> 0
A164: M04-ABR/2026 | B164: govbr-callback (troca code -> token, valida nonce/PKCE, persiste assinatura) | C164: EE | D164: I | E164: 7 | F164: code, state, code_verifier, id_token, access_token, hash_doc, contrato_id | G164: 3 | H164: govbr_pkce_states, assinaturas_govbr, contratos | I164: =IF(ISBLANK(C164),"",IF(L164="L","Baixa",IF(L164="A","Média",IF(L164="","","Alta")))) -> Alta | J164: =CONCATENATE(C164,L164) -> EEH | K164: =IF(ISBLANK(C164),"",IF(C164="ALI",IF(L164="L",7,IF(L164="A",10,15)),IF(C164="AIE",IF(L164="L",5,IF(L164="A",7,10)),IF(C164="SE",IF(L164="L",4,IF(L164="A",5,7)),IF(OR(C164="EE",C164="CE"),IF(L164="L",3,IF(L164="A",4,6)),0))))) -> 6 | L164: =IF(OR(ISBLANK(E164),ISBLANK(G164)),IF(OR(C164="ALI",C164="AIE"),"L",IF(OR(C164="EE",C164="SE",C164="CE"),"A","")),IF(C164="EE",IF(G164>=3,IF(E164>=5,"H","A"),IF(G164>=2,IF(E164>=16,"H",IF(E164<=4,"L","A")),IF(E164<=15,"L","A"))),IF(OR(C164="SE",C164="CE"),IF(G164>=4,IF(E164>=6,"H","A"),IF(G164>=2,IF(E164>=20,"H",IF(E164<=5,"L","A")),IF(E164<=19,"L","A"))),IF(OR(C164="ALI",C164="AIE"),IF(G164>=6,IF(E164>=20,"H","A"),IF(G164>=2,IF(E164>=51,"H",IF(E164<=19,"L","A")),IF(E164<=50,"L","A"))),"")))) -> H | M164: =CONCATENATE(C164,D164) -> EEI | N164: =IF(OR(K164="",K164=0),O164,K164) -> 6 | O164: =IFERROR(IF(NOT(ISERROR(VLOOKUP(C164,'Deflatores Sisp'!G$42:H$70,2,FALSE))),VLOOKUP(C164,'Deflatores Sisp'!G$42:H$70,2,FALSE),IF(OR(ISBLANK(D164),ISBLANK(C164)),"",VLOOKUP(D164,'Deflatores Sisp'!G$4:H$38,2,FALSE)*K164+VLOOKUP(D164,'Deflatores Sisp'!G$4:I$38,3,FALSE)))*W164,"") -> 5.7 | P164: x | Q164: x | R164: x | S164: x | T164: x | W164: =IF(V164="",SUM(Z164:AE164),IF(C164="PA",E164,100%)) -> 0.95 | Z164: =IF(P164="x",25%,0) -> 0.25 | AA164: =IF(Q164="x",10%,0) -> 0.1 | AB164: =IF(R164="x",40%,0) -> 0.4 | AC164: =IF(S164="x",15%,0) -> 0.15 | AD164: =IF(T164="x",5%,0) -> 0.05 | AE164: =IF(U164="x",5%,0) -> 0
A165: M04-ABR/2026 | B165: govbr-sign-init (geração PKCE + redirect IDP.SP) | C165: EE | D165: I | E165: 5 | F165: contrato_id, hash_doc, code_challenge, state, redirect_uri | G165: 2 | H165: govbr_sign_states, contratos | I165: =IF(ISBLANK(C165),"",IF(L165="L","Baixa",IF(L165="A","Média",IF(L165="","","Alta")))) -> Média | J165: =CONCATENATE(C165,L165) -> EEA | K165: =IF(ISBLANK(C165),"",IF(C165="ALI",IF(L165="L",7,IF(L165="A",10,15)),IF(C165="AIE",IF(L165="L",5,IF(L165="A",7,10)),IF(C165="SE",IF(L165="L",4,IF(L165="A",5,7)),IF(OR(C165="EE",C165="CE"),IF(L165="L",3,IF(L165="A",4,6)),0))))) -> 4 | L165: =IF(OR(ISBLANK(E165),ISBLANK(G165)),IF(OR(C165="ALI",C165="AIE"),"L",IF(OR(C165="EE",C165="SE",C165="CE"),"A","")),IF(C165="EE",IF(G165>=3,IF(E165>=5,"H","A"),IF(G165>=2,IF(E165>=16,"H",IF(E165<=4,"L","A")),IF(E165<=15,"L","A"))),IF(OR(C165="SE",C165="CE"),IF(G165>=4,IF(E165>=6,"H","A"),IF(G165>=2,IF(E165>=20,"H",IF(E165<=5,"L","A")),IF(E165<=19,"L","A"))),IF(OR(C165="ALI",C165="AIE"),IF(G165>=6,IF(E165>=20,"H","A"),IF(G165>=2,IF(E165>=51,"H",IF(E165<=19,"L","A")),IF(E165<=50,"L","A"))),"")))) -> A | M165: =CONCATENATE(C165,D165) -> EEI | N165: =IF(OR(K165="",K165=0),O165,K165) -> 4 | O165: =IFERROR(IF(NOT(ISERROR(VLOOKUP(C165,'Deflatores Sisp'!G$42:H$70,2,FALSE))),VLOOKUP(C165,'Deflatores Sisp'!G$42:H$70,2,FALSE),IF(OR(ISBLANK(D165),ISBLANK(C165)),"",VLOOKUP(D165,'Deflatores Sisp'!G$4:H$38,2,FALSE)*K165+VLOOKUP(D165,'Deflatores Sisp'!G$4:I$38,3,FALSE)))*W165,"") -> 3.8 | P165: x | Q165: x | R165: x | S165: x | T165: x | W165: =IF(V165="",SUM(Z165:AE165),IF(C165="PA",E165,100%)) -> 0.95 | Z165: =IF(P165="x",25%,0) -> 0.25 | AA165: =IF(Q165="x",10%,0) -> 0.1 | AB165: =IF(R165="x",40%,0) -> 0.4 | AC165: =IF(S165="x",15%,0) -> 0.15 | AD165: =IF(T165="x",5%,0) -> 0.05 | AE165: =IF(U165="x",5%,0) -> 0
A166: M04-ABR/2026 | B166: enviar-nf-kafka (proxy REST -> Kafka, lote multi-RPS) | C166: EE | D166: I | E166: 8 | F166: rps_ids[], cnpj, valor, serie, lote_id, callback_url, tentativas, retorno | G166: 3 | H166: documentos_fiscais, kafka_nf_lotes, erp_retornos | I166: =IF(ISBLANK(C166),"",IF(L166="L","Baixa",IF(L166="A","Média",IF(L166="","","Alta")))) -> Alta | J166: =CONCATENATE(C166,L166) -> EEH | K166: =IF(ISBLANK(C166),"",IF(C166="ALI",IF(L166="L",7,IF(L166="A",10,15)),IF(C166="AIE",IF(L166="L",5,IF(L166="A",7,10)),IF(C166="SE",IF(L166="L",4,IF(L166="A",5,7)),IF(OR(C166="EE",C166="CE"),IF(L166="L",3,IF(L166="A",4,6)),0))))) -> 6 | L166: =IF(OR(ISBLANK(E166),ISBLANK(G166)),IF(OR(C166="ALI",C166="AIE"),"L",IF(OR(C166="EE",C166="SE",C166="CE"),"A","")),IF(C166="EE",IF(G166>=3,IF(E166>=5,"H","A"),IF(G166>=2,IF(E166>=16,"H",IF(E166<=4,"L","A")),IF(E166<=15,"L","A"))),IF(OR(C166="SE",C166="CE"),IF(G166>=4,IF(E166>=6,"H","A"),IF(G166>=2,IF(E166>=20,"H",IF(E166<=5,"L","A")),IF(E166<=19,"L","A"))),IF(OR(C166="ALI",C166="AIE"),IF(G166>=6,IF(E166>=20,"H","A"),IF(G166>=2,IF(E166>=51,"H",IF(E166<=19,"L","A")),IF(E166<=50,"L","A"))),"")))) -> H | M166: =CONCATENATE(C166,D166) -> EEI | N166: =IF(OR(K166="",K166=0),O166,K166) -> 6 | O166: =IFERROR(IF(NOT(ISERROR(VLOOKUP(C166,'Deflatores Sisp'!G$42:H$70,2,FALSE))),VLOOKUP(C166,'Deflatores Sisp'!G$42:H$70,2,FALSE),IF(OR(ISBLANK(D166),ISBLANK(C166)),"",VLOOKUP(D166,'Deflatores Sisp'!G$4:H$38,2,FALSE)*K166+VLOOKUP(D166,'Deflatores Sisp'!G$4:I$38,3,FALSE)))*W166,"") -> 5.7 | P166: x | Q166: x | R166: x | S166: x | T166: x | W166: =IF(V166="",SUM(Z166:AE166),IF(C166="PA",E166,100%)) -> 0.95 | Z166: =IF(P166="x",25%,0) -> 0.25 | AA166: =IF(Q166="x",10%,0) -> 0.1 | AB166: =IF(R166="x",40%,0) -> 0.4 | AC166: =IF(S166="x",15%,0) -> 0.15 | AD166: =IF(T166="x",5%,0) -> 0.05 | AE166: =IF(U166="x",5%,0) -> 0
A167: M04-ABR/2026 | B167: sync-cliente-erp (XPRO_WS_IFACE_CLIENTES — payload completo) | C167: EE | D167: I | E167: 12 | F167: cpf_cnpj, razao, endereço, ie, ccm, flags fiscais, responsável, etc. | G167: 2 | H167: clientes, erp_retornos | I167: =IF(ISBLANK(C167),"",IF(L167="L","Baixa",IF(L167="A","Média",IF(L167="","","Alta")))) -> Média | J167: =CONCATENATE(C167,L167) -> EEA | K167: =IF(ISBLANK(C167),"",IF(C167="ALI",IF(L167="L",7,IF(L167="A",10,15)),IF(C167="AIE",IF(L167="L",5,IF(L167="A",7,10)),IF(C167="SE",IF(L167="L",4,IF(L167="A",5,7)),IF(OR(C167="EE",C167="CE"),IF(L167="L",3,IF(L167="A",4,6)),0))))) -> 4 | L167: =IF(OR(ISBLANK(E167),ISBLANK(G167)),IF(OR(C167="ALI",C167="AIE"),"L",IF(OR(C167="EE",C167="SE",C167="CE"),"A","")),IF(C167="EE",IF(G167>=3,IF(E167>=5,"H","A"),IF(G167>=2,IF(E167>=16,"H",IF(E167<=4,"L","A")),IF(E167<=15,"L","A"))),IF(OR(C167="SE",C167="CE"),IF(G167>=4,IF(E167>=6,"H","A"),IF(G167>=2,IF(E167>=20,"H",IF(E167<=5,"L","A")),IF(E167<=19,"L","A"))),IF(OR(C167="ALI",C167="AIE"),IF(G167>=6,IF(E167>=20,"H","A"),IF(G167>=2,IF(E167>=51,"H",IF(E167<=19,"L","A")),IF(E167<=50,"L","A"))),"")))) -> A | M167: =CONCATENATE(C167,D167) -> EEI | N167: =IF(OR(K167="",K167=0),O167,K167) -> 4 | O167: =IFERROR(IF(NOT(ISERROR(VLOOKUP(C167,'Deflatores Sisp'!G$42:H$70,2,FALSE))),VLOOKUP(C167,'Deflatores Sisp'!G$42:H$70,2,FALSE),IF(OR(ISBLANK(D167),ISBLANK(C167)),"",VLOOKUP(D167,'Deflatores Sisp'!G$4:H$38,2,FALSE)*K167+VLOOKUP(D167,'Deflatores Sisp'!G$4:I$38,3,FALSE)))*W167,"") -> 3.8 | P167: x | Q167: x | R167: x | S167: x | T167: x | W167: =IF(V167="",SUM(Z167:AE167),IF(C167="PA",E167,100%)) -> 0.95 | Z167: =IF(P167="x",25%,0) -> 0.25 | AA167: =IF(Q167="x",10%,0) -> 0.1 | AB167: =IF(R167="x",40%,0) -> 0.4 | AC167: =IF(S167="x",15%,0) -> 0.15 | AD167: =IF(T167="x",5%,0) -> 0.05 | AE167: =IF(U167="x",5%,0) -> 0
A168: M04-ABR/2026 | B168: Geração automática DPS/RPS no fechamento (numeração + payload fiscal) | C168: SE | D168: I | E168: 10 | F168: numero_rps, cnpj, valor, item, descrição, período, condição_pagto, etc. | G168: 2 | H168: documentos_fiscais, cobrancas | I168: =IF(ISBLANK(C168),"",IF(L168="L","Baixa",IF(L168="A","Média",IF(L168="","","Alta")))) -> Média | J168: =CONCATENATE(C168,L168) -> SEA | K168: =IF(ISBLANK(C168),"",IF(C168="ALI",IF(L168="L",7,IF(L168="A",10,15)),IF(C168="AIE",IF(L168="L",5,IF(L168="A",7,10)),IF(C168="SE",IF(L168="L",4,IF(L168="A",5,7)),IF(OR(C168="EE",C168="CE"),IF(L168="L",3,IF(L168="A",4,6)),0))))) -> 5 | L168: =IF(OR(ISBLANK(E168),ISBLANK(G168)),IF(OR(C168="ALI",C168="AIE"),"L",IF(OR(C168="EE",C168="SE",C168="CE"),"A","")),IF(C168="EE",IF(G168>=3,IF(E168>=5,"H","A"),IF(G168>=2,IF(E168>=16,"H",IF(E168<=4,"L","A")),IF(E168<=15,"L","A"))),IF(OR(C168="SE",C168="CE"),IF(G168>=4,IF(E168>=6,"H","A"),IF(G168>=2,IF(E168>=20,"H",IF(E168<=5,"L","A")),IF(E168<=19,"L","A"))),IF(OR(C168="ALI",C168="AIE"),IF(G168>=6,IF(E168>=20,"H","A"),IF(G168>=2,IF(E168>=51,"H",IF(E168<=19,"L","A")),IF(E168<=50,"L","A"))),"")))) -> A | M168: =CONCATENATE(C168,D168) -> SEI | N168: =IF(OR(K168="",K168=0),O168,K168) -> 5 | O168: =IFERROR(IF(NOT(ISERROR(VLOOKUP(C168,'Deflatores Sisp'!G$42:H$70,2,FALSE))),VLOOKUP(C168,'Deflatores Sisp'!G$42:H$70,2,FALSE),IF(OR(ISBLANK(D168),ISBLANK(C168)),"",VLOOKUP(D168,'Deflatores Sisp'!G$4:H$38,2,FALSE)*K168+VLOOKUP(D168,'Deflatores Sisp'!G$4:I$38,3,FALSE)))*W168,"") -> 4.75 | P168: x | Q168: x | R168: x | S168: x | T168: x | W168: =IF(V168="",SUM(Z168:AE168),IF(C168="PA",E168,100%)) -> 0.95 | Z168: =IF(P168="x",25%,0) -> 0.25 | AA168: =IF(Q168="x",10%,0) -> 0.1 | AB168: =IF(R168="x",40%,0) -> 0.4 | AC168: =IF(S168="x",15%,0) -> 0.15 | AD168: =IF(T168="x",5%,0) -> 0.05 | AE168: =IF(U168="x",5%,0) -> 0
A169: M04-ABR/2026 | B169: consultar-boleto-bb (2ª via Banco do Brasil) | C169: CE | D169: I | E169: 5 | F169: nosso_numero, agencia, conta, linha_digitavel, pdf_url | G169: 1 | H169: erp_retornos (lookup) | I169: =IF(ISBLANK(C169),"",IF(L169="L","Baixa",IF(L169="A","Média",IF(L169="","","Alta")))) -> Baixa | J169: =CONCATENATE(C169,L169) -> CEL | K169: =IF(ISBLANK(C169),"",IF(C169="ALI",IF(L169="L",7,IF(L169="A",10,15)),IF(C169="AIE",IF(L169="L",5,IF(L169="A",7,10)),IF(C169="SE",IF(L169="L",4,IF(L169="A",5,7)),IF(OR(C169="EE",C169="CE"),IF(L169="L",3,IF(L169="A",4,6)),0))))) -> 3 | L169: =IF(OR(ISBLANK(E169),ISBLANK(G169)),IF(OR(C169="ALI",C169="AIE"),"L",IF(OR(C169="EE",C169="SE",C169="CE"),"A","")),IF(C169="EE",IF(G169>=3,IF(E169>=5,"H","A"),IF(G169>=2,IF(E169>=16,"H",IF(E169<=4,"L","A")),IF(E169<=15,"L","A"))),IF(OR(C169="SE",C169="CE"),IF(G169>=4,IF(E169>=6,"H","A"),IF(G169>=2,IF(E169>=20,"H",IF(E169<=5,"L","A")),IF(E169<=19,"L","A"))),IF(OR(C169="ALI",C169="AIE"),IF(G169>=6,IF(E169>=20,"H","A"),IF(G169>=2,IF(E169>=51,"H",IF(E169<=19,"L","A")),IF(E169<=50,"L","A"))),"")))) -> L | M169: =CONCATENATE(C169,D169) -> CEI | N169: =IF(OR(K169="",K169=0),O169,K169) -> 3 | O169: =IFERROR(IF(NOT(ISERROR(VLOOKUP(C169,'Deflatores Sisp'!G$42:H$70,2,FALSE))),VLOOKUP(C169,'Deflatores Sisp'!G$42:H$70,2,FALSE),IF(OR(ISBLANK(D169),ISBLANK(C169)),"",VLOOKUP(D169,'Deflatores Sisp'!G$4:H$38,2,FALSE)*K169+VLOOKUP(D169,'Deflatores Sisp'!G$4:I$38,3,FALSE)))*W169,"") -> 2.85 | P169: x | Q169: x | R169: x | S169: x | T169: x | W169: =IF(V169="",SUM(Z169:AE169),IF(C169="PA",E169,100%)) -> 0.95 | Z169: =IF(P169="x",25%,0) -> 0.25 | AA169: =IF(Q169="x",10%,0) -> 0.1 | AB169: =IF(R169="x",40%,0) -> 0.4 | AC169: =IF(S169="x",15%,0) -> 0.15 | AD169: =IF(T169="x",5%,0) -> 0.05 | AE169: =IF(U169="x",5%,0) -> 0
A170: M04-ABR/2026 | B170: faturamento unificada + faturamento_itens (multi-origem) | C170: ALI | D170: A | E170: 18 | F170: mes_ref, origem, contrato, cliente, qtd, valores, gratuidade, status, etc. | G170: 3 | H170: faturamento, faturamento_itens, valores_servico_faturavel | I170: =IF(ISBLANK(C170),"",IF(L170="L","Baixa",IF(L170="A","Média",IF(L170="","","Alta")))) -> Baixa | J170: =CONCATENATE(C170,L170) -> ALIL | K170: =IF(ISBLANK(C170),"",IF(C170="ALI",IF(L170="L",7,IF(L170="A",10,15)),IF(C170="AIE",IF(L170="L",5,IF(L170="A",7,10)),IF(C170="SE",IF(L170="L",4,IF(L170="A",5,7)),IF(OR(C170="EE",C170="CE"),IF(L170="L",3,IF(L170="A",4,6)),0))))) -> 7 | L170: =IF(OR(ISBLANK(E170),ISBLANK(G170)),IF(OR(C170="ALI",C170="AIE"),"L",IF(OR(C170="EE",C170="SE",C170="CE"),"A","")),IF(C170="EE",IF(G170>=3,IF(E170>=5,"H","A"),IF(G170>=2,IF(E170>=16,"H",IF(E170<=4,"L","A")),IF(E170<=15,"L","A"))),IF(OR(C170="SE",C170="CE"),IF(G170>=4,IF(E170>=6,"H","A"),IF(G170>=2,IF(E170>=20,"H",IF(E170<=5,"L","A")),IF(E170<=19,"L","A"))),IF(OR(C170="ALI",C170="AIE"),IF(G170>=6,IF(E170>=20,"H","A"),IF(G170>=2,IF(E170>=51,"H",IF(E170<=19,"L","A")),IF(E170<=50,"L","A"))),"")))) -> L | M170: =CONCATENATE(C170,D170) -> ALIA | N170: =IF(OR(K170="",K170=0),O170,K170) -> 7 | O170: =IFERROR(IF(NOT(ISERROR(VLOOKUP(C170,'Deflatores Sisp'!G$42:H$70,2,FALSE))),VLOOKUP(C170,'Deflatores Sisp'!G$42:H$70,2,FALSE),IF(OR(ISBLANK(D170),ISBLANK(C170)),"",VLOOKUP(D170,'Deflatores Sisp'!G$4:H$38,2,FALSE)*K170+VLOOKUP(D170,'Deflatores Sisp'!G$4:I$38,3,FALSE)))*W170,"") -> 5.32 | P170: x | Q170: x | R170: x | S170: x | T170: x | W170: =IF(V170="",SUM(Z170:AE170),IF(C170="PA",E170,100%)) -> 0.95 | Z170: =IF(P170="x",25%,0) -> 0.25 | AA170: =IF(Q170="x",10%,0) -> 0.1 | AB170: =IF(R170="x",40%,0) -> 0.4 | AC170: =IF(S170="x",15%,0) -> 0.15 | AD170: =IF(T170="x",5%,0) -> 0.05 | AE170: =IF(U170="x",5%,0) -> 0
A171: M04-ABR/2026 | B171: Alteração ALI perfis — unificação "Cliente" + matriz Helpdesk N1 | C171: ALI | D171: A | E171: 5 | F171: nome, descricao, classes_cliente, sistemas_origem, permissões | G171: 3 | H171: perfis, perfil_permissoes, perfil_classes_cliente | I171: =IF(ISBLANK(C171),"",IF(L171="L","Baixa",IF(L171="A","Média",IF(L171="","","Alta")))) -> Baixa | J171: =CONCATENATE(C171,L171) -> ALIL | K171: =IF(ISBLANK(C171),"",IF(C171="ALI",IF(L171="L",7,IF(L171="A",10,15)),IF(C171="AIE",IF(L171="L",5,IF(L171="A",7,10)),IF(C171="SE",IF(L171="L",4,IF(L171="A",5,7)),IF(OR(C171="EE",C171="CE"),IF(L171="L",3,IF(L171="A",4,6)),0))))) -> 7 | L171: =IF(OR(ISBLANK(E171),ISBLANK(G171)),IF(OR(C171="ALI",C171="AIE"),"L",IF(OR(C171="EE",C171="SE",C171="CE"),"A","")),IF(C171="EE",IF(G171>=3,IF(E171>=5,"H","A"),IF(G171>=2,IF(E171>=16,"H",IF(E171<=4,"L","A")),IF(E171<=15,"L","A"))),IF(OR(C171="SE",C171="CE"),IF(G171>=4,IF(E171>=6,"H","A"),IF(G171>=2,IF(E171>=20,"H",IF(E171<=5,"L","A")),IF(E171<=19,"L","A"))),IF(OR(C171="ALI",C171="AIE"),IF(G171>=6,IF(E171>=20,"H","A"),IF(G171>=2,IF(E171>=51,"H",IF(E171<=19,"L","A")),IF(E171<=50,"L","A"))),"")))) -> L | M171: =CONCATENATE(C171,D171) -> ALIA | N171: =IF(OR(K171="",K171=0),O171,K171) -> 7 | O171: =IFERROR(IF(NOT(ISERROR(VLOOKUP(C171,'Deflatores Sisp'!G$42:H$70,2,FALSE))),VLOOKUP(C171,'Deflatores Sisp'!G$42:H$70,2,FALSE),IF(OR(ISBLANK(D171),ISBLANK(C171)),"",VLOOKUP(D171,'Deflatores Sisp'!G$4:H$38,2,FALSE)*K171+VLOOKUP(D171,'Deflatores Sisp'!G$4:I$38,3,FALSE)))*W171,"") -> 5.32 | P171: x | Q171: x | R171: x | S171: x | T171: x | W171: =IF(V171="",SUM(Z171:AE171),IF(C171="PA",E171,100%)) -> 0.95 | Z171: =IF(P171="x",25%,0) -> 0.25 | AA171: =IF(Q171="x",10%,0) -> 0.1 | AB171: =IF(R171="x",40%,0) -> 0.4 | AC171: =IF(S171="x",15%,0) -> 0.15 | AD171: =IF(T171="x",5%,0) -> 0.05 | AE171: =IF(U171="x",5%,0) -> 0
A172: M04-ABR/2026 | B172: Exclusão dos perfis legados "Clientes – Financeiro" e "Suporte" | C172: EE | D172: E | E172: 2 | F172: perfil_id, motivo | G172: 3 | H172: perfil_permissoes, perfil_classes_cliente, perfil_sistemas | I172: =IF(ISBLANK(C172),"",IF(L172="L","Baixa",IF(L172="A","Média",IF(L172="","","Alta")))) -> Média | J172: =CONCATENATE(C172,L172) -> EEA | K172: =IF(ISBLANK(C172),"",IF(C172="ALI",IF(L172="L",7,IF(L172="A",10,15)),IF(C172="AIE",IF(L172="L",5,IF(L172="A",7,10)),IF(C172="SE",IF(L172="L",4,IF(L172="A",5,7)),IF(OR(C172="EE",C172="CE"),IF(L172="L",3,IF(L172="A",4,6)),0))))) -> 4 | L172: =IF(OR(ISBLANK(E172),ISBLANK(G172)),IF(OR(C172="ALI",C172="AIE"),"L",IF(OR(C172="EE",C172="SE",C172="CE"),"A","")),IF(C172="EE",IF(G172>=3,IF(E172>=5,"H","A"),IF(G172>=2,IF(E172>=16,"H",IF(E172<=4,"L","A")),IF(E172<=15,"L","A"))),IF(OR(C172="SE",C172="CE"),IF(G172>=4,IF(E172>=6,"H","A"),IF(G172>=2,IF(E172>=20,"H",IF(E172<=5,"L","A")),IF(E172<=19,"L","A"))),IF(OR(C172="ALI",C172="AIE"),IF(G172>=6,IF(E172>=20,"H","A"),IF(G172>=2,IF(E172>=51,"H",IF(E172<=19,"L","A")),IF(E172<=50,"L","A"))),"")))) -> A | M172: =CONCATENATE(C172,D172) -> EEE | N172: =IF(OR(K172="",K172=0),O172,K172) -> 4 | O172: =IFERROR(IF(NOT(ISERROR(VLOOKUP(C172,'Deflatores Sisp'!G$42:H$70,2,FALSE))),VLOOKUP(C172,'Deflatores Sisp'!G$42:H$70,2,FALSE),IF(OR(ISBLANK(D172),ISBLANK(C172)),"",VLOOKUP(D172,'Deflatores Sisp'!G$4:H$38,2,FALSE)*K172+VLOOKUP(D172,'Deflatores Sisp'!G$4:I$38,3,FALSE)))*W172,"") -> 1.52 | P172: x | Q172: x | R172: x | S172: x | T172: x | W172: =IF(V172="",SUM(Z172:AE172),IF(C172="PA",E172,100%)) -> 0.95 | Z172: =IF(P172="x",25%,0) -> 0.25 | AA172: =IF(Q172="x",10%,0) -> 0.1 | AB172: =IF(R172="x",40%,0) -> 0.4 | AC172: =IF(S172="x",15%,0) -> 0.15 | AD172: =IF(T172="x",5%,0) -> 0.05 | AE172: =IF(U172="x",5%,0) -> 0
A173: M04-ABR/2026 | B173: Criar Cliente Detran/Poupatempo/Consignatários (3 edge fns) | C173: EE | D173: I | E173: 10 | F173: cnpj, razao, endereco, responsavel, sistema, modulo, validacoes | G173: 2 | H173: clientes + sistemas_origem | I173: =IF(ISBLANK(C173),"",IF(L173="L","Baixa",IF(L173="A","Média",IF(L173="","","Alta")))) -> Média | J173: =CONCATENATE(C173,L173) -> EEA | K173: =IF(ISBLANK(C173),"",IF(C173="ALI",IF(L173="L",7,IF(L173="A",10,15)),IF(C173="AIE",IF(L173="L",5,IF(L173="A",7,10)),IF(C173="SE",IF(L173="L",4,IF(L173="A",5,7)),IF(OR(C173="EE",C173="CE"),IF(L173="L",3,IF(L173="A",4,6)),0))))) -> 4 | L173: =IF(OR(ISBLANK(E173),ISBLANK(G173)),IF(OR(C173="ALI",C173="AIE"),"L",IF(OR(C173="EE",C173="SE",C173="CE"),"A","")),IF(C173="EE",IF(G173>=3,IF(E173>=5,"H","A"),IF(G173>=2,IF(E173>=16,"H",IF(E173<=4,"L","A")),IF(E173<=15,"L","A"))),IF(OR(C173="SE",C173="CE"),IF(G173>=4,IF(E173>=6,"H","A"),IF(G173>=2,IF(E173>=20,"H",IF(E173<=5,"L","A")),IF(E173<=19,"L","A"))),IF(OR(C173="ALI",C173="AIE"),IF(G173>=6,IF(E173>=20,"H","A"),IF(G173>=2,IF(E173>=51,"H",IF(E173<=19,"L","A")),IF(E173<=50,"L","A"))),"")))) -> A | M173: =CONCATENATE(C173,D173) -> EEI | N173: =IF(OR(K173="",K173=0),O173,K173) -> 4 | O173: =IFERROR(IF(NOT(ISERROR(VLOOKUP(C173,'Deflatores Sisp'!G$42:H$70,2,FALSE))),VLOOKUP(C173,'Deflatores Sisp'!G$42:H$70,2,FALSE),IF(OR(ISBLANK(D173),ISBLANK(C173)),"",VLOOKUP(D173,'Deflatores Sisp'!G$4:H$38,2,FALSE)*K173+VLOOKUP(D173,'Deflatores Sisp'!G$4:I$38,3,FALSE)))*W173,"") -> 3.8 | P173: x | Q173: x | R173: x | S173: x | T173: x | W173: =IF(V173="",SUM(Z173:AE173),IF(C173="PA",E173,100%)) -> 0.95 | Z173: =IF(P173="x",25%,0) -> 0.25 | AA173: =IF(Q173="x",10%,0) -> 0.1 | AB173: =IF(R173="x",40%,0) -> 0.4 | AC173: =IF(S173="x",15%,0) -> 0.15 | AD173: =IF(T173="x",5%,0) -> 0.05 | AE173: =IF(U173="x",5%,0) -> 0
A174: M04-ABR/2026 | B174: Baixa Manual Boleto / Religação / Divergência (3 fluxos) | C174: EE | D174: I | E174: 7 | F174: cobranca_id, valor_pago, data, motivo, usuario, anexo, status | G174: 2 | H174: cobrancas + pagamentos | I174: =IF(ISBLANK(C174),"",IF(L174="L","Baixa",IF(L174="A","Média",IF(L174="","","Alta")))) -> Média | J174: =CONCATENATE(C174,L174) -> EEA | K174: =IF(ISBLANK(C174),"",IF(C174="ALI",IF(L174="L",7,IF(L174="A",10,15)),IF(C174="AIE",IF(L174="L",5,IF(L174="A",7,10)),IF(C174="SE",IF(L174="L",4,IF(L174="A",5,7)),IF(OR(C174="EE",C174="CE"),IF(L174="L",3,IF(L174="A",4,6)),0))))) -> 4 | L174: =IF(OR(ISBLANK(E174),ISBLANK(G174)),IF(OR(C174="ALI",C174="AIE"),"L",IF(OR(C174="EE",C174="SE",C174="CE"),"A","")),IF(C174="EE",IF(G174>=3,IF(E174>=5,"H","A"),IF(G174>=2,IF(E174>=16,"H",IF(E174<=4,"L","A")),IF(E174<=15,"L","A"))),IF(OR(C174="SE",C174="CE"),IF(G174>=4,IF(E174>=6,"H","A"),IF(G174>=2,IF(E174>=20,"H",IF(E174<=5,"L","A")),IF(E174<=19,"L","A"))),IF(OR(C174="ALI",C174="AIE"),IF(G174>=6,IF(E174>=20,"H","A"),IF(G174>=2,IF(E174>=51,"H",IF(E174<=19,"L","A")),IF(E174<=50,"L","A"))),"")))) -> A | M174: =CONCATENATE(C174,D174) -> EEI | N174: =IF(OR(K174="",K174=0),O174,K174) -> 4 | O174: =IFERROR(IF(NOT(ISERROR(VLOOKUP(C174,'Deflatores Sisp'!G$42:H$70,2,FALSE))),VLOOKUP(C174,'Deflatores Sisp'!G$42:H$70,2,FALSE),IF(OR(ISBLANK(D174),ISBLANK(C174)),"",VLOOKUP(D174,'Deflatores Sisp'!G$4:H$38,2,FALSE)*K174+VLOOKUP(D174,'Deflatores Sisp'!G$4:I$38,3,FALSE)))*W174,"") -> 3.8 | P174: x | Q174: x | R174: x | S174: x | T174: x | W174: =IF(V174="",SUM(Z174:AE174),IF(C174="PA",E174,100%)) -> 0.95 | Z174: =IF(P174="x",25%,0) -> 0.25 | AA174: =IF(Q174="x",10%,0) -> 0.1 | AB174: =IF(R174="x",40%,0) -> 0.4 | AC174: =IF(S174="x",15%,0) -> 0.15 | AD174: =IF(T174="x",5%,0) -> 0.05 | AE174: =IF(U174="x",5%,0) -> 0
... A189: M04-ABR/2026 | B189: sync-cliente-erp (XPRO_WS_IFACE_CLIENTES) | C189: EE | D189: I | E189: 14 | F189: cpf_cnpj, razão, endereço, IE, CCM, flags fiscais, responsável, IBGE, etc. | G189: 2 | H189: clientes, erp_retornos | I189: =IF(ISBLANK(C189),"",IF(L189="L","Baixa",IF(L189="A","Média",IF(L189="","","Alta")))) -> Média | J189: =CONCATENATE(C189,L189) -> EEA | K189: =IF(ISBLANK(C189),"",IF(C189="ALI",IF(L189="L",7,IF(L189="A",10,15)),IF(C189="AIE",IF(L189="L",5,IF(L189="A",7,10)),IF(C189="SE",IF(L189="L",4,IF(L189="A",5,7)),IF(OR(C189="EE",C189="CE"),IF(L189="L",3,IF(L189="A",4,6)),0))))) -> 4 | L189: =IF(OR(ISBLANK(E189),ISBLANK(G189)),IF(OR(C189="ALI",C189="AIE"),"L",IF(OR(C189="EE",C189="SE",C189="CE"),"A","")),IF(C189="EE",IF(G189>=3,IF(E189>=5,"H","A"),IF(G189>=2,IF(E189>=16,"H",IF(E189<=4,"L","A")),IF(E189<=15,"L","A"))),IF(OR(C189="SE",C189="CE"),IF(G189>=4,IF(E189>=6,"H","A"),IF(G189>=2,IF(E189>=20,"H",IF(E189<=5,"L","A")),IF(E189<=19,"L","A"))),IF(OR(C189="ALI",C189="AIE"),IF(G189>=6,IF(E189>=20,"H","A"),IF(G189>=2,IF(E189>=51,"H",IF(E189<=19,"L","A")),IF(E189<=50,"L","A"))),"")))) -> A | M189: =CONCATENATE(C189,D189) -> EEI | N189: =IF(OR(K189="",K189=0),O189,K189) -> 4 | O189: =IFERROR(IF(NOT(ISERROR(VLOOKUP(C189,'Deflatores Sisp'!G$42:H$70,2,FALSE))),VLOOKUP(C189,'Deflatores Sisp'!G$42:H$70,2,FALSE),IF(OR(ISBLANK(D189),ISBLANK(C189)),"",VLOOKUP(D189,'Deflatores Sisp'!G$4:H$38,2,FALSE)*K189+VLOOKUP(D189,'Deflatores Sisp'!G$4:I$38,3,FALSE)))*W189,"") -> 3.8 | P189: x | Q189: x | R189: x | S189: x | T189: x | W189: =IF(V189="",SUM(Z189:AE189),IF(C189="PA",E189,100%)) -> 0.95 | Z189: =IF(P189="x",25%,0) -> 0.25 | AA189: =IF(Q189="x",10%,0) -> 0.1 | AB189: =IF(R189="x",40%,0) -> 0.4 | AC189: =IF(S189="x",15%,0) -> 0.15 | AD189: =IF(T189="x",5%,0) -> 0.05 | AE189: =IF(U189="x",5%,0) -> 0
A190: M04-ABR/2026 | B190: enviar-documentos-erp (assíncrono) | C190: EE | D190: I | E190: 8 | F190: docs[], modulo, mes_ref, payload, callback, tentativas | G190: 3 | H190: documentos_fiscais, erp_retornos, cobrancas | I190: =IF(ISBLANK(C190),"",IF(L190="L","Baixa",IF(L190="A","Média",IF(L190="","","Alta")))) -> Alta | J190: =CONCATENATE(C190,L190) -> EEH | K190: =IF(ISBLANK(C190),"",IF(C190="ALI",IF(L190="L",7,IF(L190="A",10,15)),IF(C190="AIE",IF(L190="L",5,IF(L190="A",7,10)),IF(C190="SE",IF(L190="L",4,IF(L190="A",5,7)),IF(OR(C190="EE",C190="CE"),IF(L190="L",3,IF(L190="A",4,6)),0))))) -> 6 | L190: =IF(OR(ISBLANK(E190),ISBLANK(G190)),IF(OR(C190="ALI",C190="AIE"),"L",IF(OR(C190="EE",C190="SE",C190="CE"),"A","")),IF(C190="EE",IF(G190>=3,IF(E190>=5,"H","A"),IF(G190>=2,IF(E190>=16,"H",IF(E190<=4,"L","A")),IF(E190<=15,"L","A"))),IF(OR(C190="SE",C190="CE"),IF(G190>=4,IF(E190>=6,"H","A"),IF(G190>=2,IF(E190>=20,"H",IF(E190<=5,"L","A")),IF(E190<=19,"L","A"))),IF(OR(C190="ALI",C190="AIE"),IF(G190>=6,IF(E190>=20,"H","A"),IF(G190>=2,IF(E190>=51,"H",IF(E190<=19,"L","A")),IF(E190<=50,"L","A"))),"")))) -> H | M190: =CONCATENATE(C190,D190) -> EEI | N190: =IF(OR(K190="",K190=0),O190,K190) -> 6 | O190: =IFERROR(IF(NOT(ISERROR(VLOOKUP(C190,'Deflatores Sisp'!G$42:H$70,2,FALSE))),VLOOKUP(C190,'Deflatores Sisp'!G$42:H$70,2,FALSE),IF(OR(ISBLANK(D190),ISBLANK(C190)),"",VLOOKUP(D190,'Deflatores Sisp'!G$4:H$38,2,FALSE)*K190+VLOOKUP(D190,'Deflatores Sisp'!G$4:I$38,3,FALSE)))*W190,"") -> 5.4 | P190: x | Q190: x | R190: x | S190: x | W190: =IF(V190="",SUM(Z190:AE190),IF(C190="PA",E190,100%)) -> 0.9 | Z190: =IF(P190="x",25%,0) -> 0.25 | AA190: =IF(Q190="x",10%,0) -> 0.1 | AB190: =IF(R190="x",40%,0) -> 0.4 | AC190: =IF(S190="x",15%,0) -> 0.15 | AD190: =IF(T190="x",5%,0) -> 0 | AE190: =IF(U190="x",5%,0) -> 0
A191: M04-ABR/2026 | B191: Geração automática DPS/RPS no fechamento | C191: SE | D191: I | E191: 10 | F191: numero_rps, cnpj, valor, item, descrição, período, tipo_nota, série | G191: 2 | H191: documentos_fiscais, cobrancas | I191: =IF(ISBLANK(C191),"",IF(L191="L","Baixa",IF(L191="A","Média",IF(L191="","","Alta")))) -> Média | J191: =CONCATENATE(C191,L191) -> SEA | K191: =IF(ISBLANK(C191),"",IF(C191="ALI",IF(L191="L",7,IF(L191="A",10,15)),IF(C191="AIE",IF(L191="L",5,IF(L191="A",7,10)),IF(C191="SE",IF(L191="L",4,IF(L191="A",5,7)),IF(OR(C191="EE",C191="CE"),IF(L191="L",3,IF(L191="A",4,6)),0))))) -> 5 | L191: =IF(OR(ISBLANK(E191),ISBLANK(G191)),IF(OR(C191="ALI",C191="AIE"),"L",IF(OR(C191="EE",C191="SE",C191="CE"),"A","")),IF(C191="EE",IF(G191>=3,IF(E191>=5,"H","A"),IF(G191>=2,IF(E191>=16,"H",IF(E191<=4,"L","A")),IF(E191<=15,"L","A"))),IF(OR(C191="SE",C191="CE"),IF(G191>=4,IF(E191>=6,"H","A"),IF(G191>=2,IF(E191>=20,"H",IF(E191<=5,"L","A")),IF(E191<=19,"L","A"))),IF(OR(C191="ALI",C191="AIE"),IF(G191>=6,IF(E191>=20,"H","A"),IF(G191>=2,IF(E191>=51,"H",IF(E191<=19,"L","A")),IF(E191<=50,"L","A"))),"")))) -> A | M191: =CONCATENATE(C191,D191) -> SEI | N191: =IF(OR(K191="",K191=0),O191,K191) -> 5 | O191: =IFERROR(IF(NOT(ISERROR(VLOOKUP(C191,'Deflatores Sisp'!G$42:H$70,2,FALSE))),VLOOKUP(C191,'Deflatores Sisp'!G$42:H$70,2,FALSE),IF(OR(ISBLANK(D191),ISBLANK(C191)),"",VLOOKUP(D191,'Deflatores Sisp'!G$4:H$38,2,FALSE)*K191+VLOOKUP(D191,'Deflatores Sisp'!G$4:I$38,3,FALSE)))*W191,"") -> 4.75 | P191: x | Q191: x | R191: x | S191: x | T191: x | W191: =IF(V191="",SUM(Z191:AE191),IF(C191="PA",E191,100%)) -> 0.95 | Z191: =IF(P191="x",25%,0) -> 0.25 | AA191: =IF(Q191="x",10%,0) -> 0.1 | AB191: =IF(R191="x",40%,0) -> 0.4 | AC191: =IF(S191="x",15%,0) -> 0.15 | AD191: =IF(T191="x",5%,0) -> 0.05 | AE191: =IF(U191="x",5%,0) -> 0
A192: M04-ABR/2026 | B192: consultar-boleto-bb (2ª via BB) | C192: CE | D192: I | E192: 5 | F192: nosso_numero, agência, conta, linha_digitavel, pdf_url | G192: 1 | H192: erp_retornos (lookup) | I192: =IF(ISBLANK(C192),"",IF(L192="L","Baixa",IF(L192="A","Média",IF(L192="","","Alta")))) -> Baixa | J192: =CONCATENATE(C192,L192) -> CEL | K192: =IF(ISBLANK(C192),"",IF(C192="ALI",IF(L192="L",7,IF(L192="A",10,15)),IF(C192="AIE",IF(L192="L",5,IF(L192="A",7,10)),IF(C192="SE",IF(L192="L",4,IF(L192="A",5,7)),IF(OR(C192="EE",C192="CE"),IF(L192="L",3,IF(L192="A",4,6)),0))))) -> 3 | L192: =IF(OR(ISBLANK(E192),ISBLANK(G192)),IF(OR(C192="ALI",C192="AIE"),"L",IF(OR(C192="EE",C192="SE",C192="CE"),"A","")),IF(C192="EE",IF(G192>=3,IF(E192>=5,"H","A"),IF(G192>=2,IF(E192>=16,"H",IF(E192<=4,"L","A")),IF(E192<=15,"L","A"))),IF(OR(C192="SE",C192="CE"),IF(G192>=4,IF(E192>=6,"H","A"),IF(G192>=2,IF(E192>=20,"H",IF(E192<=5,"L","A")),IF(E192<=19,"L","A"))),IF(OR(C192="ALI",C192="AIE"),IF(G192>=6,IF(E192>=20,"H","A"),IF(G192>=2,IF(E192>=51,"H",IF(E192<=19,"L","A")),IF(E192<=50,"L","A"))),"")))) -> L | M192: =CONCATENATE(C192,D192) -> CEI | N192: =IF(OR(K192="",K192=0),O192,K192) -> 3 | O192: =IFERROR(IF(NOT(ISERROR(VLOOKUP(C192,'Deflatores Sisp'!G$42:H$70,2,FALSE))),VLOOKUP(C192,'Deflatores Sisp'!G$42:H$70,2,FALSE),IF(OR(ISBLANK(D192),ISBLANK(C192)),"",VLOOKUP(D192,'Deflatores Sisp'!G$4:H$38,2,FALSE)*K192+VLOOKUP(D192,'Deflatores Sisp'!G$4:I$38,3,FALSE)))*W192,"") -> 2.85 | P192: x | Q192: x | R192: x | S192: x | T192: x | W192: =IF(V192="",SUM(Z192:AE192),IF(C192="PA",E192,100%)) -> 0.95 | Z192: =IF(P192="x",25%,0) -> 0.25 | AA192: =IF(Q192="x",10%,0) -> 0.1 | AB192: =IF(R192="x",40%,0) -> 0.4 | AC192: =IF(S192="x",15%,0) -> 0.15 | AD192: =IF(T192="x",5%,0) -> 0.05 | AE192: =IF(U192="x",5%,0) -> 0
A193: M04-ABR/2026 | B193: faturamento unificada (multi-origem) | C193: ALI | D193: A | E193: 18 | F193: mes_ref, origem, contrato, cliente, qtd, valores, gratuidade, status, etc. | G193: 3 | H193: faturamento, faturamento_itens, valores_servico_faturavel | I193: =IF(ISBLANK(C193),"",IF(L193="L","Baixa",IF(L193="A","Média",IF(L193="","","Alta")))) -> Baixa | J193: =CONCATENATE(C193,L193) -> ALIL | K193: =IF(ISBLANK(C193),"",IF(C193="ALI",IF(L193="L",7,IF(L193="A",10,15)),IF(C193="AIE",IF(L193="L",5,IF(L193="A",7,10)),IF(C193="SE",IF(L193="L",4,IF(L193="A",5,7)),IF(OR(C193="EE",C193="CE"),IF(L193="L",3,IF(L193="A",4,6)),0))))) -> 7 | L193: =IF(OR(ISBLANK(E193),ISBLANK(G193)),IF(OR(C193="ALI",C193="AIE"),"L",IF(OR(C193="EE",C193="SE",C193="CE"),"A","")),IF(C193="EE",IF(G193>=3,IF(E193>=5,"H","A"),IF(G193>=2,IF(E193>=16,"H",IF(E193<=4,"L","A")),IF(E193<=15,"L","A"))),IF(OR(C193="SE",C193="CE"),IF(G193>=4,IF(E193>=6,"H","A"),IF(G193>=2,IF(E193>=20,"H",IF(E193<=5,"L","A")),IF(E193<=19,"L","A"))),IF(OR(C193="ALI",C193="AIE"),IF(G193>=6,IF(E193>=20,"H","A"),IF(G193>=2,IF(E193>=51,"H",IF(E193<=19,"L","A")),IF(E193<=50,"L","A"))),"")))) -> L | M193: =CONCATENATE(C193,D193) -> ALIA | N193: =IF(OR(K193="",K193=0),O193,K193) -> 7 | O193: =IFERROR(IF(NOT(ISERROR(VLOOKUP(C193,'Deflatores Sisp'!G$42:H$70,2,FALSE))),VLOOKUP(C193,'Deflatores Sisp'!G$42:H$70,2,FALSE),IF(OR(ISBLANK(D193),ISBLANK(C193)),"",VLOOKUP(D193,'Deflatores Sisp'!G$4:H$38,2,FALSE)*K193+VLOOKUP(D193,'Deflatores Sisp'!G$4:I$38,3,FALSE)))*W193,"") -> 5.32 | P193: x | Q193: x | R193: x | S193: x | T193: x | W193: =IF(V193="",SUM(Z193:AE193),IF(C193="PA",E193,100%)) -> 0.95 | Z193: =IF(P193="x",25%,0) -> 0.25 | AA193: =IF(Q193="x",10%,0) -> 0.1 | AB193: =IF(R193="x",40%,0) -> 0.4 | AC193: =IF(S193="x",15%,0) -> 0.15 | AD193: =IF(T193="x",5%,0) -> 0.05 | AE193: =IF(U193="x",5%,0) -> 0
A194: M04-ABR/2026 | B194: faturamento_itens (detalhados) | C194: ALI | D194: I | E194: 9 | F194: faturamento_id, tipo_item, código_serviço, descrição, qtd, vl_unit, vl_total | G194: 2 | H194: faturamento_itens, servicos_faturaveis | I194: =IF(ISBLANK(C194),"",IF(L194="L","Baixa",IF(L194="A","Média",IF(L194="","","Alta")))) -> Baixa | J194: =CONCATENATE(C194,L194) -> ALIL | K194: =IF(ISBLANK(C194),"",IF(C194="ALI",IF(L194="L",7,IF(L194="A",10,15)),IF(C194="AIE",IF(L194="L",5,IF(L194="A",7,10)),IF(C194="SE",IF(L194="L",4,IF(L194="A",5,7)),IF(OR(C194="EE",C194="CE"),IF(L194="L",3,IF(L194="A",4,6)),0))))) -> 7 | L194: =IF(OR(ISBLANK(E194),ISBLANK(G194)),IF(OR(C194="ALI",C194="AIE"),"L",IF(OR(C194="EE",C194="SE",C194="CE"),"A","")),IF(C194="EE",IF(G194>=3,IF(E194>=5,"H","A"),IF(G194>=2,IF(E194>=16,"H",IF(E194<=4,"L","A")),IF(E194<=15,"L","A"))),IF(OR(C194="SE",C194="CE"),IF(G194>=4,IF(E194>=6,"H","A"),IF(G194>=2,IF(E194>=20,"H",IF(E194<=5,"L","A")),IF(E194<=19,"L","A"))),IF(OR(C194="ALI",C194="AIE"),IF(G194>=6,IF(E194>=20,"H","A"),IF(G194>=2,IF(E194>=51,"H",IF(E194<=19,"L","A")),IF(E194<=50,"L","A"))),"")))) -> L | M194: =CONCATENATE(C194,D194) -> ALII | N194: =IF(OR(K194="",K194=0),O194,K194) -> 7 | O194: =IFERROR(IF(NOT(ISERROR(VLOOKUP(C194,'Deflatores Sisp'!G$42:H$70,2,FALSE))),VLOOKUP(C194,'Deflatores Sisp'!G$42:H$70,2,FALSE),IF(OR(ISBLANK(D194),ISBLANK(C194)),"",VLOOKUP(D194,'Deflatores Sisp'!G$4:H$38,2,FALSE)*K194+VLOOKUP(D194,'Deflatores Sisp'!G$4:I$38,3,FALSE)))*W194,"") -> 6.65 | P194: x | Q194: x | R194: x | S194: x | T194: x | W194: =IF(V194="",SUM(Z194:AE194),IF(C194="PA",E194,100%)) -> 0.95 | Z194: =IF(P194="x",25%,0) -> 0.25 | AA194: =IF(Q194="x",10%,0) -> 0.1 | AB194: =IF(R194="x",40%,0) -> 0.4 | AC194: =IF(S194="x",15%,0) -> 0.15 | AD194: =IF(T194="x",5%,0) -> 0.05 | AE194: =IF(U194="x",5%,0) -> 0
A195: M04-ABR/2026 | B195: consolidar-faturamento-detran v2 | C195: EE | D195: I | E195: 9 | F195: mes_ref, sistema, registros, cliente_id, contrato_id, vl_unit, classe | G195: 4 | H195: bilhetagem_ecnh, bilhetagem_ecrv, faturamento, valores | I195: =IF(ISBLANK(C195),"",IF(L195="L","Baixa",IF(L195="A","Média",IF(L195="","","Alta")))) -> Alta | J195: =CONCATENATE(C195,L195) -> EEH | K195: =IF(ISBLANK(C195),"",IF(C195="ALI",IF(L195="L",7,IF(L195="A",10,15)),IF(C195="AIE",IF(L195="L",5,IF(L195="A",7,10)),IF(C195="SE",IF(L195="L",4,IF(L195="A",5,7)),IF(OR(C195="EE",C195="CE"),IF(L195="L",3,IF(L195="A",4,6)),0))))) -> 6 | L195: =IF(OR(ISBLANK(E195),ISBLANK(G195)),IF(OR(C195="ALI",C195="AIE"),"L",IF(OR(C195="EE",C195="SE",C195="CE"),"A","")),IF(C195="EE",IF(G195>=3,IF(E195>=5,"H","A"),IF(G195>=2,IF(E195>=16,"H",IF(E195<=4,"L","A")),IF(E195<=15,"L","A"))),IF(OR(C195="SE",C195="CE"),IF(G195>=4,IF(E195>=6,"H","A"),IF(G195>=2,IF(E195>=20,"H",IF(E195<=5,"L","A")),IF(E195<=19,"L","A"))),IF(OR(C195="ALI",C195="AIE"),IF(G195>=6,IF(E195>=20,"H","A"),IF(G195>=2,IF(E195>=51,"H",IF(E195<=19,"L","A")),IF(E195<=50,"L","A"))),"")))) -> H | M195: =CONCATENATE(C195,D195) -> EEI | N195: =IF(OR(K195="",K195=0),O195,K195) -> 6 | O195: =IFERROR(IF(NOT(ISERROR(VLOOKUP(C195,'Deflatores Sisp'!G$42:H$70,2,FALSE))),VLOOKUP(C195,'Deflatores Sisp'!G$42:H$70,2,FALSE),IF(OR(ISBLANK(D195),ISBLANK(C195)),"",VLOOKUP(D195,'Deflatores Sisp'!G$4:H$38,2,FALSE)*K195+VLOOKUP(D195,'Deflatores Sisp'!G$4:I$38,3,FALSE)))*W195,"") -> 5.7 | P195: x | Q195: x | R195: x | S195: x | T195: x | W195: =IF(V195="",SUM(Z195:AE195),IF(C195="PA",E195,100%)) -> 0.95 | Z195: =IF(P195="x",25%,0) -> 0.25 | AA195: =IF(Q195="x",10%,0) -> 0.1 | AB195: =IF(R195="x",40%,0) -> 0.4 | AC195: =IF(S195="x",15%,0) -> 0.15 | AD195: =IF(T195="x",5%,0) -> 0.05 | AE195: =IF(U195="x",5%,0) -> 0
A196: M04-ABR/2026 | B196: Relatório de Faturamento Excel | C196: SE | D196: I | E196: 12 | F196: mes_ref, abas sistema, cliente, contrato, qtd, vl_unit, vl_total, totais | G196: 4 | H196: faturamento, faturamento_itens, clientes, contratos | I196: =IF(ISBLANK(C196),"",IF(L196="L","Baixa",IF(L196="A","Média",IF(L196="","","Alta")))) -> Alta | J196: =CONCATENATE(C196,L196) -> SEH | K196: =IF(ISBLANK(C196),"",IF(C196="ALI",IF(L196="L",7,IF(L196="A",10,15)),IF(C196="AIE",IF(L196="L",5,IF(L196="A",7,10)),IF(C196="SE",IF(L196="L",4,IF(L196="A",5,7)),IF(OR(C196="EE",C196="CE"),IF(L196="L",3,IF(L196="A",4,6)),0))))) -> 7 | L196: =IF(OR(ISBLANK(E196),ISBLANK(G196)),IF(OR(C196="ALI",C196="AIE"),"L",IF(OR(C196="EE",C196="SE",C196="CE"),"A","")),IF(C196="EE",IF(G196>=3,IF(E196>=5,"H","A"),IF(G196>=2,IF(E196>=16,"H",IF(E196<=4,"L","A")),IF(E196<=15,"L","A"))),IF(OR(C196="SE",C196="CE"),IF(G196>=4,IF(E196>=6,"H","A"),IF(G196>=2,IF(E196>=20,"H",IF(E196<=5,"L","A")),IF(E196<=19,"L","A"))),IF(OR(C196="ALI",C196="AIE"),IF(G196>=6,IF(E196>=20,"H","A"),IF(G196>=2,IF(E196>=51,"H",IF(E196<=19,"L","A")),IF(E196<=50,"L","A"))),"")))) -> H | M196: =CONCATENATE(C196,D196) -> SEI | N196: =IF(OR(K196="",K196=0),O196,K196) -> 7 | O196: =IFERROR(IF(NOT(ISERROR(VLOOKUP(C196,'Deflatores Sisp'!G$42:H$70,2,FALSE))),VLOOKUP(C196,'Deflatores Sisp'!G$42:H$70,2,FALSE),IF(OR(ISBLANK(D196),ISBLANK(C196)),"",VLOOKUP(D196,'Deflatores Sisp'!G$4:H$38,2,FALSE)*K196+VLOOKUP(D196,'Deflatores Sisp'!G$4:I$38,3,FALSE)))*W196,"") -> 6.3 | P196: x | Q196: x | R196: x | S196: x | W196: =IF(V196="",SUM(Z196:AE196),IF(C196="PA",E196,100%)) -> 0.9 | Z196: =IF(P196="x",25%,0) -> 0.25 | AA196: =IF(Q196="x",10%,0) -> 0.1 | AB196: =IF(R196="x",40%,0) -> 0.4 | AC196: =IF(S196="x",15%,0) -> 0.15 | AD196: =IF(T196="x",5%,0) -> 0 | AE196: =IF(U196="x",5%,0) -> 0
A197: M04-ABR/2026 | B197: integrar-bilhetagem-ecrv (REST proxy) | C197: EE | D197: I | E197: 10 | F197: data_ref, cpf, cod_ssp, doc_consultado, retorno, trx, ident | G197: 2 | H197: bilhetagem_ecrv, integracao_execucoes | I197: =IF(ISBLANK(C197),"",IF(L197="L","Baixa",IF(L197="A","Média",IF(L197="","","Alta")))) -> Média | J197: =CONCATENATE(C197,L197) -> EEA | K197: =IF(ISBLANK(C197),"",IF(C197="ALI",IF(L197="L",7,IF(L197="A",10,15)),IF(C197="AIE",IF(L197="L",5,IF(L197="A",7,10)),IF(C197="SE",IF(L197="L",4,IF(L197="A",5,7)),IF(OR(C197="EE",C197="CE"),IF(L197="L",3,IF(L197="A",4,6)),0))))) -> 4 | L197: =IF(OR(ISBLANK(E197),ISBLANK(G197)),IF(OR(C197="ALI",C197="AIE"),"L",IF(OR(C197="EE",C197="SE",C197="CE"),"A","")),IF(C197="EE",IF(G197>=3,IF(E197>=5,"H","A"),IF(G197>=2,IF(E197>=16,"H",IF(E197<=4,"L","A")),IF(E197<=15,"L","A"))),IF(OR(C197="SE",C197="CE"),IF(G197>=4,IF(E197>=6,"H","A"),IF(G197>=2,IF(E197>=20,"H",IF(E197<=5,"L","A")),IF(E197<=19,"L","A"))),IF(OR(C197="ALI",C197="AIE"),IF(G197>=6,IF(E197>=20,"H","A"),IF(G197>=2,IF(E197>=51,"H",IF(E197<=19,"L","A")),IF(E197<=50,"L","A"))),"")))) -> A | M197: =CONCATENATE(C197,D197) -> EEI | N197: =IF(OR(K197="",K197=0),O197,K197) -> 4 | O197: =IFERROR(IF(NOT(ISERROR(VLOOKUP(C197,'Deflatores Sisp'!G$42:H$70,2,FALSE))),VLOOKUP(C197,'Deflatores Sisp'!G$42:H$70,2,FALSE),IF(OR(ISBLANK(D197),ISBLANK(C197)),"",VLOOKUP(D197,'Deflatores Sisp'!G$4:H$38,2,FALSE)*K197+VLOOKUP(D197,'Deflatores Sisp'!G$4:I$38,3,FALSE)))*W197,"") -> 3.8 | P197: x | Q197: x | R197: x | S197: x | T197: x | W197: =IF(V197="",SUM(Z197:AE197),IF(C197="PA",E197,100%)) -> 0.95 | Z197: =IF(P197="x",25%,0) -> 0.25 | AA197: =IF(Q197="x",10%,0) -> 0.1 | AB197: =IF(R197="x",40%,0) -> 0.4 | AC197: =IF(S197="x",15%,0) -> 0.15 | AD197: =IF(T197="x",5%,0) -> 0.05 | AE197: =IF(U197="x",5%,0) -> 0
A198: M04-ABR/2026 | B198: integrar-bilhetagem-consignatarios | C198: EE | D198: I | E198: 8 | F198: mes_ref, código_entidade, contrato, grupo, proposta, qtd, sedex | G198: 2 | H198: bilhetagem_consignatarios, integracao_execucoes | I198: =IF(ISBLANK(C198),"",IF(L198="L","Baixa",IF(L198="A","Média",IF(L198="","","Alta")))) -> Média | J198: =CONCATENATE(C198,L198) -> EEA | K198: =IF(ISBLANK(C198),"",IF(C198="ALI",IF(L198="L",7,IF(L198="A",10,15)),IF(C198="AIE",IF(L198="L",5,IF(L198="A",7,10)),IF(C198="SE",IF(L198="L",4,IF(L198="A",5,7)),IF(OR(C198="EE",C198="CE"),IF(L198="L",3,IF(L198="A",4,6)),0))))) -> 4 | L198: =IF(OR(ISBLANK(E198),ISBLANK(G198)),IF(OR(C198="ALI",C198="AIE"),"L",IF(OR(C198="EE",C198="SE",C198="CE"),"A","")),IF(C198="EE",IF(G198>=3,IF(E198>=5,"H","A"),IF(G198>=2,IF(E198>=16,"H",IF(E198<=4,"L","A")),IF(E198<=15,"L","A"))),IF(OR(C198="SE",C198="CE"),IF(G198>=4,IF(E198>=6,"H","A"),IF(G198>=2,IF(E198>=20,"H",IF(E198<=5,"L","A")),IF(E198<=19,"L","A"))),IF(OR(C198="ALI",C198="AIE"),IF(G198>=6,IF(E198>=20,"H","A"),IF(G198>=2,IF(E198>=51,"H",IF(E198<=19,"L","A")),IF(E198<=50,"L","A"))),"")))) -> A | M198: =CONCATENATE(C198,D198) -> EEI | N198: =IF(OR(K198="",K198=0),O198,K198) -> 4 | O198: =IFERROR(IF(NOT(ISERROR(VLOOKUP(C198,'Deflatores Sisp'!G$42:H$70,2,FALSE))),VLOOKUP(C198,'Deflatores Sisp'!G$42:H$70,2,FALSE),IF(OR(ISBLANK(D198),ISBLANK(C198)),"",VLOOKUP(D198,'Deflatores Sisp'!G$4:H$38,2,FALSE)*K198+VLOOKUP(D198,'Deflatores Sisp'!G$4:I$38,3,FALSE)))*W198,"") -> 3.8 | P198: x | Q198: x | R198: x | S198: x | T198: x | W198: =IF(V198="",SUM(Z198:AE198),IF(C198="PA",E198,100%)) -> 0.95 | Z198: =IF(P198="x",25%,0) -> 0.25 | AA198: =IF(Q198="x",10%,0) -> 0.1 | AB198: =IF(R198="x",40%,0) -> 0.4 | AC198: =IF(S198="x",15%,0) -> 0.15 | AD198: =IF(T198="x",5%,0) -> 0.05 | AE198: =IF(U198="x",5%,0) -> 0
A199: M04-ABR/2026 | B199: processar-bilhetagem-credenciados (CSV) | C199: EE | D199: I | E199: 9 | F199: requisição_id, classe, CNPJ, código_serviço, qtd, mes_ref | G199: 2 | H199: bilhetagem_portal_credenciados, historico_requisicoes_credenciados | I199: =IF(ISBLANK(C199),"",IF(L199="L","Baixa",IF(L199="A","Média",IF(L199="","","Alta")))) -> Média | J199: =CONCATENATE(C199,L199) -> EEA | K199: =IF(ISBLANK(C199),"",IF(C199="ALI",IF(L199="L",7,IF(L199="A",10,15)),IF(C199="AIE",IF(L199="L",5,IF(L199="A",7,10)),IF(C199="SE",IF(L199="L",4,IF(L199="A",5,7)),IF(OR(C199="EE",C199="CE"),IF(L199="L",3,IF(L199="A",4,6)),0))))) -> 4 | L199: =IF(OR(ISBLANK(E199),ISBLANK(G199)),IF(OR(C199="ALI",C199="AIE"),"L",IF(OR(C199="EE",C199="SE",C199="CE"),"A","")),IF(C199="EE",IF(G199>=3,IF(E199>=5,"H","A"),IF(G199>=2,IF(E199>=16,"H",IF(E199<=4,"L","A")),IF(E199<=15,"L","A"))),IF(OR(C199="SE",C199="CE"),IF(G199>=4,IF(E199>=6,"H","A"),IF(G199>=2,IF(E199>=20,"H",IF(E199<=5,"L","A")),IF(E199<=19,"L","A"))),IF(OR(C199="ALI",C199="AIE"),IF(G199>=6,IF(E199>=20,"H","A"),IF(G199>=2,IF(E199>=51,"H",IF(E199<=19,"L","A")),IF(E199<=50,"L","A"))),"")))) -> A | M199: =CONCATENATE(C199,D199) -> EEI | N199: =IF(OR(K199="",K199=0),O199,K199) -> 4 | O199: =IFERROR(IF(NOT(ISERROR(VLOOKUP(C199,'Deflatores Sisp'!G$42:H$70,2,FALSE))),VLOOKUP(C199,'Deflatores Sisp'!G$42:H$70,2,FALSE),IF(OR(ISBLANK(D199),ISBLANK(C199)),"",VLOOKUP(D199,'Deflatores Sisp'!G$4:H$38,2,FALSE)*K199+VLOOKUP(D199,'Deflatores Sisp'!G$4:I$38,3,FALSE)))*W199,"") -> 3.8 | P199: x | Q199: x | R199: x | S199: x | T199: x | W199: =IF(V199="",SUM(Z199:AE199),IF(C199="PA",E199,100%)) -> 0.95 | Z199: =IF(P199="x",25%,0) -> 0.25 | AA199: =IF(Q199="x",10%,0) -> 0.1 | AB199: =IF(R199="x",40%,0) -> 0.4 | AC199: =IF(S199="x",15%,0) -> 0.15 | AD199: =IF(T199="x",5%,0) -> 0.05 | AE199: =IF(U199="x",5%,0) -> 0
A200: M04-ABR/2026 | B200: enviar-convite-usuario (token SHA-256) | C200: EE | D200: I | E200: 6 | F200: email, role, token_hash, expires_at, redirect_url, criado_por | G200: 2 | H200: convites_usuario, profiles | I200: =IF(ISBLANK(C200),"",IF(L200="L","Baixa",IF(L200="A","Média",IF(L200="","","Alta")))) -> Média | J200: =CONCATENATE(C200,L200) -> EEA | K200: =IF(ISBLANK(C200),"",IF(C200="ALI",IF(L200="L",7,IF(L200="A",10,15)),IF(C200="AIE",IF(L200="L",5,IF(L200="A",7,10)),IF(C200="SE",IF(L200="L",4,IF(L200="A",5,7)),IF(OR(C200="EE",C200="CE"),IF(L200="L",3,IF(L200="A",4,6)),0))))) -> 4 | L200: =IF(OR(ISBLANK(E200),ISBLANK(G200)),IF(OR(C200="ALI",C200="AIE"),"L",IF(OR(C200="EE",C200="SE",C200="CE"),"A","")),IF(C200="EE",IF(G200>=3,IF(E200>=5,"H","A"),IF(G200>=2,IF(E200>=16,"H",IF(E200<=4,"L","A")),IF(E200<=15,"L","A"))),IF(OR(C200="SE",C200="CE"),IF(G200>=4,IF(E200>=6,"H","A"),IF(G200>=2,IF(E200>=20,"H",IF(E200<=5,"L","A")),IF(E200<=19,"L","A"))),IF(OR(C200="ALI",C200="AIE"),IF(G200>=6,IF(E200>=20,"H","A"),IF(G200>=2,IF(E200>=51,"H",IF(E200<=19,"L","A")),IF(E200<=50,"L","A"))),"")))) -> A | M200: =CONCATENATE(C200,D200) -> EEI | N200: =IF(OR(K200="",K200=0),O200,K200) -> 4 | O200: =IFERROR(IF(NOT(ISERROR(VLOOKUP(C200,'Deflatores Sisp'!G$42:H$70,2,FALSE))),VLOOKUP(C200,'Deflatores Sisp'!G$42:H$70,2,FALSE),IF(OR(ISBLANK(D200),ISBLANK(C200)),"",VLOOKUP(D200,'Deflatores Sisp'!G$4:H$38,2,FALSE)*K200+VLOOKUP(D200,'Deflatores Sisp'!G$4:I$38,3,FALSE)))*W200,"") -> 3.6 | P200: x | Q200: x | R200: x | S200: x | W200: =IF(V200="",SUM(Z200:AE200),IF(C200="PA",E200,100%)) -> 0.9 | Z200: =IF(P200="x",25%,0) -> 0.25 | AA200: =IF(Q200="x",10%,0) -> 0.1 | AB200: =IF(R200="x",40%,0) -> 0.4 | AC200: =IF(S200="x",15%,0) -> 0.15 | AD200: =IF(T200="x",5%,0) -> 0 | AE200: =IF(U200="x",5%,0) -> 0
A201: M04-ABR/2026 | B201: api-v1-clientes (consulta + filtros) | C201: CE | D201: I | E201: 12 | F201: cpf_cnpj, razão, status, tipo_cliente, perfis_esp, paginação | G201: 3 | H201: clientes, cliente_tipos_entidade, api_access_logs | I201: =IF(ISBLANK(C201),"",IF(L201="L","Baixa",IF(L201="A","Média",IF(L201="","","Alta")))) -> Média | J201: =CONCATENATE(C201,L201) -> CEA | K201: =IF(ISBLANK(C201),"",IF(C201="ALI",IF(L201="L",7,IF(L201="A",10,15)),IF(C201="AIE",IF(L201="L",5,IF(L201="A",7,10)),IF(C201="SE",IF(L201="L",4,IF(L201="A",5,7)),IF(OR(C201="EE",C201="CE"),IF(L201="L",3,IF(L201="A",4,6)),0))))) -> 4 | L201: =IF(OR(ISBLANK(E201),ISBLANK(G201)),IF(OR(C201="ALI",C201="AIE"),"L",IF(OR(C201="EE",C201="SE",C201="CE"),"A","")),IF(C201="EE",IF(G201>=3,IF(E201>=5,"H","A"),IF(G201>=2,IF(E201>=16,"H",IF(E201<=4,"L","A")),IF(E201<=15,"L","A"))),IF(OR(C201="SE",C201="CE"),IF(G201>=4,IF(E201>=6,"H","A"),IF(G201>=2,IF(E201>=20,"H",IF(E201<=5,"L","A")),IF(E201<=19,"L","A"))),IF(OR(C201="ALI",C201="AIE"),IF(G201>=6,IF(E201>=20,"H","A"),IF(G201>=2,IF(E201>=51,"H",IF(E201<=19,"L","A")),IF(E201<=50,"L","A"))),"")))) -> A | M201: =CONCATENATE(C201,D201) -> CEI | N201: =IF(OR(K201="",K201=0),O201,K201) -> 4 | O201: =IFERROR(IF(NOT(ISERROR(VLOOKUP(C201,'Deflatores Sisp'!G$42:H$70,2,FALSE))),VLOOKUP(C201,'Deflatores Sisp'!G$42:H$70,2,FALSE),IF(OR(ISBLANK(D201),ISBLANK(C201)),"",VLOOKUP(D201,'Deflatores Sisp'!G$4:H$38,2,FALSE)*K201+VLOOKUP(D201,'Deflatores Sisp'!G$4:I$38,3,FALSE)))*W201,"") -> 3.6 | P201: x | Q201: x | R201: x | S201: x | W201: =IF(V201="",SUM(Z201:AE201),IF(C201="PA",E201,100%)) -> 0.9 | Z201: =IF(P201="x",25%,0) -> 0.25 | AA201: =IF(Q201="x",10%,0) -> 0.1 | AB201: =IF(R201="x",40%,0) -> 0.4 | AC201: =IF(S201="x",15%,0) -> 0.15 | AD201: =IF(T201="x",5%,0) -> 0 | AE201: =IF(U201="x",5%,0) -> 0
A202: M04-ABR/2026 | B202: api-v1-contratos (consulta escopo) | C202: CE | D202: I | E202: 10 | F202: numero_contrato, status, sistema, cliente, datas, paginação | G202: 3 | H202: contratos, clientes, api_access_logs | I202: =IF(ISBLANK(C202),"",IF(L202="L","Baixa",IF(L202="A","Média",IF(L202="","","Alta")))) -> Média | J202: =CONCATENATE(C202,L202) -> CEA | K202: =IF(ISBLANK(C202),"",IF(C202="ALI",IF(L202="L",7,IF(L202="A",10,15)),IF(C202="AIE",IF(L202="L",5,IF(L202="A",7,10)),IF(C202="SE",IF(L202="L",4,IF(L202="A",5,7)),IF(OR(C202="EE",C202="CE"),IF(L202="L",3,IF(L202="A",4,6)),0))))) -> 4 | L202: =IF(OR(ISBLANK(E202),ISBLANK(G202)),IF(OR(C202="ALI",C202="AIE"),"L",IF(OR(C202="EE",C202="SE",C202="CE"),"A","")),IF(C202="EE",IF(G202>=3,IF(E202>=5,"H","A"),IF(G202>=2,IF(E202>=16,"H",IF(E202<=4,"L","A")),IF(E202<=15,"L","A"))),IF(OR(C202="SE",C202="CE"),IF(G202>=4,IF(E202>=6,"H","A"),IF(G202>=2,IF(E202>=20,"H",IF(E202<=5,"L","A")),IF(E202<=19,"L","A"))),IF(OR(C202="ALI",C202="AIE"),IF(G202>=6,IF(E202>=20,"H","A"),IF(G202>=2,IF(E202>=51,"H",IF(E202<=19,"L","A")),IF(E202<=50,"L","A"))),"")))) -> A | M202: =CONCATENATE(C202,D202) -> CEI | N202: =IF(OR(K202="",K202=0),O202,K202) -> 4 | O202: =IFERROR(IF(NOT(ISERROR(VLOOKUP(C202,'Deflatores Sisp'!G$42:H$70,2,FALSE))),VLOOKUP(C202,'Deflatores Sisp'!G$42:H$70,2,FALSE),IF(OR(ISBLANK(D202),ISBLANK(C202)),"",VLOOKUP(D202,'Deflatores Sisp'!G$4:H$38,2,FALSE)*K202+VLOOKUP(D202,'Deflatores Sisp'!G$4:I$38,3,FALSE)))*W202,"") -> 3.8 | P202: x | Q202: x | R202: x | S202: x | T202: x | W202: =IF(V202="",SUM(Z202:AE202),IF(C202="PA",E202,100%)) -> 0.95 | Z202: =IF(P202="x",25%,0) -> 0.25 | AA202: =IF(Q202="x",10%,0) -> 0.1 | AB202: =IF(R202="x",40%,0) -> 0.4 | AC202: =IF(S202="x",15%,0) -> 0.15 | AD202: =IF(T202="x",5%,0) -> 0.05 | AE202: =IF(U202="x",5%,0) -> 0

Sheet Deflatores Sisp
A1: Itens Não Mensuráveis
A2: Tipo de Manutenção na Função | G2: Sigla | H2: Contribuição em PF Local | J2: PF IFPUG | K2: PF Local FS | L2: Fator Disciplina | M2: Tamanho Ajustado | N2: =SUM(L4:L38) -> 24.05
A3: Contrato | B3: Descrição | F3: Origem | H3: Percentual (%) | I3: Fixa (PF)
A4: SISP 2.3 | B4: Inclusão | G4: I | H4: 1 | J4: =SUMIF(Funções!$D$8:$D$104,'Deflatores Sisp'!G4,Funções!$K$8:$K$104) -> 481 | K4: =IF(H4="",COUNTIF(Funções!D$8:D$104,G4)*I4,H4*J4) -> 481 | L4: =SUMIF(Funções!$D$8:$D$104,'Deflatores Sisp'!G4,Funções!$O$8:$O$104) -> 24.05 | M4: EvolutivaI
A5: SISP 2.3 | B5: Alteração (sem conhecimento do Fator de Impacto) | F5: SISP – 4.2 Projeto de Melhoria | G5: A | H5: 0.8 | J5: =SUMIF(Funções!$D$8:$D$104,'Deflatores Sisp'!G5,Funções!$K$8:$K$104) -> 0 | K5: =IF(H5="",COUNTIF(Funções!D$8:D$104,G5)*I5,H5*J5) -> 0 | L5: =SUMIF(Funções!$D$8:$D$104,'Deflatores Sisp'!G5,Funções!$O$8:$O$104) -> 0 | M5: EvolutivaA
A6: SISP 2.3 | B6: Exclusão | F6: SISP – 4.2 Projeto de Melhoria | G6: E | H6: 0.4 | J6: =SUMIF(Funções!$D$8:$D$104,'Deflatores Sisp'!G6,Funções!$K$8:$K$104) -> 0 | K6: =IF(H6="",COUNTIF(Funções!D$8:D$104,G6)*I6,H6*J6) -> 0 | L6: =SUMIF(Funções!$D$8:$D$104,'Deflatores Sisp'!G6,Funções!$O$8:$O$104) -> 0 | M6: EvolutivaE
A7: SISP 2.3 | B7: Alteração (50%) de função desenvolvida ou já alterada pela empresa atual | F7: SISP – 4.2 Projeto de Melhoria | G7: A50 | H7: 0.5 | J7: =SUMIF(Funções!$D$8:$D$104,'Deflatores Sisp'!G7,Funções!$K$8:$K$104) -> 0 | K7: =IF(H7="",COUNTIF(Funções!D$8:D$104,G7)*I7,H7*J7) -> 0 | L7: =SUMIF(Funções!$D$8:$D$104,'Deflatores Sisp'!G7,Funções!$O$8:$O$104) -> 0 | M7: EvolutivaA
A8: SISP 2.3 | B8: FI = 75% para funcionalidade de sistema não desenvolvida ou mantida por meio de um projeto de melhoria pela empresa contratada e sem necessidade de redocumentação da funcionalidade. | F8: SISP – 4.2 Projeto de Melhoria | G8: A75 | H8: 0.75 | J8: =SUMIF(Funções!$D$8:$D$104,'Deflatores Sisp'!G8,Funções!$K$8:$K$104) -> 0 | K8: =IF(H8="",COUNTIF(Funções!D$8:D$104,G8)*I8,H8*J8) -> 0 | L8: =SUMIF(Funções!$D$8:$D$104,'Deflatores Sisp'!G8,Funções!$O$8:$O$104) -> 0 | M8: EvolutivaA
A9: SISP 2.3 | B9: Alteração (75%+15%): o mesmo acima + redocumentar a função | F9: SISP – 4.2 Projeto de Melhoria | G9: A90 | H9: 0.9 | J9: =SUMIF(Funções!$D$8:$D$104,'Deflatores Sisp'!G9,Funções!$K$8:$K$104) -> 0 | K9: =IF(H9="",COUNTIF(Funções!D$8:D$104,G9)*I9,H9*J9) -> 0 | L9: =SUMIF(Funções!$D$8:$D$104,'Deflatores Sisp'!G9,Funções!$O$8:$O$104) -> 0 | M9: EvolutivaA
A10: SISP 2.3 | B10: Migração de Dados | F10: SISP – 4.3 Projetos de Migração de Dados | G10: PMD | H10: 1 | J10: =SUMIF(Funções!$D$8:$D$104,'Deflatores Sisp'!G10,Funções!$K$8:$K$104) -> 0 | K10: =IF(H10="",COUNTIF(Funções!D$8:D$104,G10)*I10,H10*J10) -> 0 | L10: =SUMIF(Funções!$D$8:$D$104,'Deflatores Sisp'!G10,Funções!$O$8:$O$104) -> 0 | M10: EvolutivaI
A11: SISP 2.3 | B11: Corretiva (sem conhecimento do Fator de Impacto) | F11: SISP – 4.4 Manutenção Corretiva | G11: COR | H11: 0.5 | J11: =SUMIF(Funções!$D$8:$D$104,'Deflatores Sisp'!G11,Funções!$K$8:$K$104) -> 0 | K11: =IF(H11="",COUNTIF(Funções!D$8:D$104,G11)*I11,H11*J11) -> 0 | L11: =SUMIF(Funções!$D$8:$D$104,'Deflatores Sisp'!G11,Funções!$O$8:$O$104) -> 0 | M11: CORRETIVA
A12: SISP 2.3 | B12: Corretiva (50%) - Fora da garantia (mesma empresa) | F12: SISP – 4.4 Manutenção Corretiva | G12: COR50 | H12: 0.5 | J12: =SUMIF(Funções!$D$8:$D$104,'Deflatores Sisp'!G12,Funções!$K$8:$K$104) -> 0 | K12: =IF(H12="",COUNTIF(Funções!D$8:D$104,G12)*I12,H12*J12) -> 0 | L12: =SUMIF(Funções!$D$8:$D$104,'Deflatores Sisp'!G12,Funções!$O$8:$O$104) -> 0 | M12: CORRETIVA
A13: SISP 2.3 | B13: Corretiva (75%) - Fora da garantia (outra empresa) | F13: SISP – 4.4 Manutenção Corretiva | G13: COR75 | H13: 0.75 | J13: =SUMIF(Funções!$D$8:$D$104,'Deflatores Sisp'!G13,Funções!$K$8:$K$104) -> 0 | K13: =IF(H13="",COUNTIF(Funções!D$8:D$104,G13)*I13,H13*J13) -> 0 | L13: =SUMIF(Funções!$D$8:$D$104,'Deflatores Sisp'!G13,Funções!$O$8:$O$104) -> 0 | M13: CORRETIVA
A14: SISP 2.3 | B14: Corretiva (75%+15%) - Fora da garantia (outra empresa) + Redocumentação | F14: SISP – 4.4 Manutenção Corretiva | G14: COR90 | H14: 0.9 | J14: =SUMIF(Funções!$D$8:$D$104,'Deflatores Sisp'!G14,Funções!$K$8:$K$104) -> 0 | K14: =IF(H14="",COUNTIF(Funções!D$8:D$104,G14)*I14,H14*J14) -> 0 | L14: =SUMIF(Funções!$D$8:$D$104,'Deflatores Sisp'!G14,Funções!$O$8:$O$104) -> 0 | M14: CORRETIVA
A15: SISP 2.3 | B15: Corretiva em Garantia | F15: SISP – 4.4 Manutenção Corretiva | G15: GAR | H15: 0 | J15: =SUMIF(Funções!$D$8:$D$104,'Deflatores Sisp'!G15,Funções!$K$8:$K$104) -> 0 | K15: =IF(H15="",COUNTIF(Funções!D$8:D$104,G15)*I15,H15*J15) -> 0 | L15: =SUMIF(Funções!$D$8:$D$104,'Deflatores Sisp'!G15,Funções!$O$8:$O$104) -> 0
A16: SISP 2.3 | B16: Mudança de Plataforma - Linguagem de Programação | F16: SISP – 4.5.1 Mudança de Plataforma – Linguagem de Programação | G16: MLP | H16: 1 | J16: =SUMIF(Funções!$D$8:$D$104,'Deflatores Sisp'!G16,Funções!$K$8:$K$104) -> 0 | K16: =IF(H16="",COUNTIF(Funções!D$8:D$104,G16)*I16,H16*J16) -> 0 | L16: =SUMIF(Funções!$D$8:$D$104,'Deflatores Sisp'!G16,Funções!$O$8:$O$104) -> 0 | M16: ADAPTATIVA
A17: SISP 2.3 | B17: Mudança de Plataforma - Banco de Dados (outro paradigma) | F17: SISP – 4.5.2 Mudança de Plataforma – Banco de Dados | G17: MBO | H17: 1 | J17: =SUMIF(Funções!$D$8:$D$104,'Deflatores Sisp'!G17,Funções!$K$8:$K$104) -> 0 | K17: =IF(H17="",COUNTIF(Funções!D$8:D$104,G17)*I17,H17*J17) -> 0 | L17: =SUMIF(Funções!$D$8:$D$104,'Deflatores Sisp'!G17,Funções!$O$8:$O$104) -> 0 | M17: ADAPTATIVA
A18: SISP 2.3 | B18: Mudança de Plataforma - Banco de Dados (mesmo paradigma com alterações) | F18: SISP – 4.5.2 Mudança de Plataforma – Banco de Dados | G18: MBM | H18: 0.3 | J18: =SUMIF(Funções!$D$8:$D$104,'Deflatores Sisp'!G18,Funções!$K$8:$K$104) -> 0 | K18: =IF(H18="",COUNTIF(Funções!D$8:D$104,G18)*I18,H18*J18) -> 0 | L18: =SUMIF(Funções!$D$8:$D$104,'Deflatores Sisp'!G18,Funções!$O$8:$O$104) -> 0 | M18: ADAPTATIVA
A19: SISP 2.3 | B19: Atualização de Versão – Linguagem de Programação | F19: SISP – 4.6.1 Atualização de Versão – Linguagem de Programação | G19: ALP | H19: 0.3 | J19: =SUMIF(Funções!$D$8:$D$104,'Deflatores Sisp'!G19,Funções!$K$8:$K$104) -> 0 | K19: =IF(H19="",COUNTIF(Funções!D$8:D$104,G19)*I19,H19*J19) -> 0 | L19: =SUMIF(Funções!$D$8:$D$104,'Deflatores Sisp'!G19,Funções!$O$8:$O$104) -> 0 | M19: ADAPTATIVA
A20: SISP 2.3 | B20: Atualização de Versão – Browser | F20: SISP – 4.6.2 Atualização de Versão – Browser | G20: AVB | H20: 0.3 | J20: =SUMIF(Funções!$D$8:$D$104,'Deflatores Sisp'!G20,Funções!$K$8:$K$104) -> 0 | K20: =IF(H20="",COUNTIF(Funções!D$8:D$104,G20)*I20,H20*J20) -> 0 | L20: =SUMIF(Funções!$D$8:$D$104,'Deflatores Sisp'!G20,Funções!$O$8:$O$104) -> 0 | M20: ADAPTATIVA
A21: SISP 2.3 | B21: Atualização de Versão – Banco de Dados | F21: SISP – 4.6.3 Atualização de Versão – Banco de Dados | G21: ABD | H21: 0.3 | J21: =SUMIF(Funções!$D$8:$D$104,'Deflatores Sisp'!G21,Funções!$K$8:$K$104) -> 0 | K21: =IF(H21="",COUNTIF(Funções!D$8:D$104,G21)*I21,H21*J21) -> 0 | L21: =SUMIF(Funções!$D$8:$D$104,'Deflatores Sisp'!G21,Funções!$O$8:$O$104) -> 0 | M21: ADAPTATIVA
A22: SISP 2.3 | B22: Manutenção Cosmética | F22: SISP – 4.7 Manutenção Cosmética | G22: COS | I22: 0.6 | J22: =SUMIF(Funções!$D$8:$D$104,'Deflatores Sisp'!G22,Funções!$K$8:$K$104) -> 0 | K22: =IF(H22="",COUNTIF(Funções!D$8:D$104,G22)*I22,H22*J22) -> 0 | L22: =SUMIF(Funções!$D$8:$D$104,'Deflatores Sisp'!G22,Funções!$O$8:$O$104) -> 0 | M22: ADAPTATIVA
A23: SISP 2.3 | B23: Adaptação em Funcionalidades sem Alteração de Requisitos Funcionais (sem conhecimento do Fator de Impacto) | F23: SISP – 4.8 Adaptação em Funcionalidades sem Alteração de Requisitos Funcionais | G23: ARN | H23: 0.5 | J23: =SUMIF(Funções!$D$8:$D$104,'Deflatores Sisp'!G23,Funções!$K$8:$K$104) -> 0 | K23: =IF(H23="",COUNTIF(Funções!D$8:D$104,G23)*I23,H23*J23) -> 0 | L23: =SUMIF(Funções!$D$8:$D$104,'Deflatores Sisp'!G23,Funções!$O$8:$O$104) -> 0 | M23: ADAPTATIVA
A24: SISP 2.3 | B24: Adaptação em Funcionalidades sem Alteração de Requisitos Funcionais (50%) (em função desenvolvida ou já alterada pela empresa atual) | F24: SISP – 4.8 Adaptação em Funcionalidades sem Alteração de Requisitos Funcionais | G24: ARN50 | H24: 0.5 | J24: =SUMIF(Funções!$D$8:$D$104,'Deflatores Sisp'!G24,Funções!$K$8:$K$104) -> 0 | K24: =IF(H24="",COUNTIF(Funções!D$8:D$104,G24)*I24,H24*J24) -> 0 | L24: =SUMIF(Funções!$D$8:$D$104,'Deflatores Sisp'!G24,Funções!$O$8:$O$104) -> 0 | M24: ADAPTATIVA
A25: SISP 2.3 | B25: Adaptação em Funcionalidades sem Alteração de Requisitos Funcionais (75%) (em função não desenvolvida e ainda não alterada pela empresa atual) | F25: SISP – 4.8 Adaptação em Funcionalidades sem Alteração de Requisitos Funcionais | G25: ARN75 | H25: 0.75 | J25: =SUMIF(Funções!$D$8:$D$104,'Deflatores Sisp'!G25,Funções!$K$8:$K$104) -> 0 | K25: =IF(H25="",COUNTIF(Funções!D$8:D$104,G25)*I25,H25*J25) -> 0 | L25: =SUMIF(Funções!$D$8:$D$104,'Deflatores Sisp'!G25,Funções!$O$8:$O$104) -> 0 | M25: ADAPTATIVA
A26: SISP 2.3 | B26: Atualização de Dados sem Consulta Prévia | F26: SISP – 4.9.1 Apuração Especial – Base de Dados | G26: ADS | H26: 1 | J26: =SUMIF(Funções!$D$8:$D$104,'Deflatores Sisp'!G26,Funções!$K$8:$K$104) -> 0 | K26: =IF(H26="",COUNTIF(Funções!D$8:D$104,G26)*I26,H26*J26) -> 0 | L26: =SUMIF(Funções!$D$8:$D$104,'Deflatores Sisp'!G26,Funções!$O$8:$O$104) -> 0 | M26: CORRETIVA
A27: SISP 2.3 | B27: Consulta Prévia sem Atualização | F27: SISP – 4.9.1 Apuração Especial – Base de Dados | G27: CPA | H27: 1 | J27: =SUMIF(Funções!$D$8:$D$104,'Deflatores Sisp'!G27,Funções!$K$8:$K$104) -> 0 | K27: =IF(H27="",COUNTIF(Funções!D$8:D$104,G27)*I27,H27*J27) -> 0 | L27: =SUMIF(Funções!$D$8:$D$104,'Deflatores Sisp'!G27,Funções!$O$8:$O$104) -> 0 | M27: CORRETIVA
A28: SISP 2.3 | B28: Atualização de Dados com Consulta Prévia | F28: SISP – 4.9.1 Apuração Especial – Base de Dados | G28: ADC | H28: 0.6 | J28: =SUMIF(Funções!$D$8:$D$104,'Deflatores Sisp'!G28,Funções!$K$8:$K$104) -> 0 | K28: =IF(H28="",COUNTIF(Funções!D$8:D$104,G28)*I28,H28*J28) -> 0 | L28: =SUMIF(Funções!$D$8:$D$104,'Deflatores Sisp'!G28,Funções!$O$8:$O$104) -> 0 | M28: CORRETIVA
A29: SISP 2.3 | B29: Apuração Especial – Geração de Relatórios | F29: SISP – 4.9.2 Apuração Especial – Geração de Relatórios | G29: AGR | H29: 1 | J29: =SUMIF(Funções!$D$8:$D$104,'Deflatores Sisp'!G29,Funções!$K$8:$K$104) -> 0 | K29: =IF(H29="",COUNTIF(Funções!D$8:D$104,G29)*I29,H29*J29) -> 0 | L29: =SUMIF(Funções!$D$8:$D$104,'Deflatores Sisp'!G29,Funções!$O$8:$O$104) -> 0 | M29: CORRETIVA
A30: SISP 2.3 | B30: Apuração Especial – Reexecução | F30: SISP – 4.9.3 Apuração Especial – Reexecução | G30: AER | H30: 0.1 | J30: =SUMIF(Funções!$D$8:$D$104,'Deflatores Sisp'!G30,Funções!$K$8:$K$104) -> 0 | K30: =IF(H30="",COUNTIF(Funções!D$8:D$104,G30)*I30,H30*J30) -> 0 | L30: =SUMIF(Funções!$D$8:$D$104,'Deflatores Sisp'!G30,Funções!$O$8:$O$104) -> 0 | M30: CORRETIVA
A31: SISP 2.3 | B31: Atualização de Dados | F31: SISP – 4.10 Atualização de Dados | G31: ATD | H31: 0.1 | J31: =SUMIF(Funções!$D$8:$D$104,'Deflatores Sisp'!G31,Funções!$K$8:$K$104) -> 0 | K31: =IF(H31="",COUNTIF(Funções!D$8:D$104,G31)*I31,H31*J31) -> 0 | L31: =SUMIF(Funções!$D$8:$D$104,'Deflatores Sisp'!G31,Funções!$O$8:$O$104) -> 0 | M31: CORRETIVA
A32: SISP 2.3 | B32: Manutenção de Documentação de Sistemas Legados | F32: SISP – 4.12 Manutenção de Documentação de Sistemas Legados | G32: MSL | H32: 0.25 | J32: =SUMIF(Funções!$D$8:$D$104,'Deflatores Sisp'!G32,Funções!$K$8:$K$104) -> 0 | K32: =IF(H32="",COUNTIF(Funções!D$8:D$104,G32)*I32,H32*J32) -> 0 | L32: =SUMIF(Funções!$D$8:$D$104,'Deflatores Sisp'!G32,Funções!$O$8:$O$104) -> 0 | M32: CORRETIVA
A33: SISP 2.3 | B33: Verificação de Erros (Sem Documentação de Teste existente) | F33: SISP – 4.13 Verificação de Erros | G33: VES | H33: 0.2 | J33: =SUMIF(Funções!$D$8:$D$104,'Deflatores Sisp'!G33,Funções!$K$8:$K$104) -> 0 | K33: =IF(H33="",COUNTIF(Funções!D$8:D$104,G33)*I33,H33*J33) -> 0 | L33: =SUMIF(Funções!$D$8:$D$104,'Deflatores Sisp'!G33,Funções!$O$8:$O$104) -> 0 | M33: CORRETIVA
A34: SISP 2.3 | B34: Verificação de Erros (Com Documentação de Teste existente) | F34: SISP – 4.13 Verificação de Erros | G34: VEC | H34: 0.15 | J34: =SUMIF(Funções!$D$8:$D$104,'Deflatores Sisp'!G34,Funções!$K$8:$K$104) -> 0 | K34: =IF(H34="",COUNTIF(Funções!D$8:D$104,G34)*I34,H34*J34) -> 0 | L34: =SUMIF(Funções!$D$8:$D$104,'Deflatores Sisp'!G34,Funções!$O$8:$O$104) -> 0 | M34: CORRETIVA
... A36: SISP 2.3 | B36: Componente Interno Reusável | F36: SISP – 4.15 Componente Interno Reusável | G36: CIR | H36: 1 | J36: =SUMIF(Funções!$D$8:$D$104,'Deflatores Sisp'!G36,Funções!$K$8:$K$104) -> 0 | K36: =IF(H36="",COUNTIF(Funções!D$8:D$104,G36)*I36,H36*J36) -> 0 | L36: =SUMIF(Funções!$D$8:$D$104,'Deflatores Sisp'!G36,Funções!$O$8:$O$104) -> 0 | M36: EvolutivaI
A37: PRODESP - TCESP | B37: Alteração em funcionalidade | F37: Confirmar com o Responsáveis!!!!! E-mail 13 de jun. de 2022 15:11 | G37: . | H37: 0.8 | J37: =SUMIF(Funções!$D$8:$D$104,'Deflatores Sisp'!G37,Funções!$K$8:$K$104) -> 0 | K37: =IF(H37="",COUNTIF(Funções!D$8:D$104,G37)*I37,H37*J37) -> 0 | M37: ALI
G38: . | J38: =SUMIF(Funções!$D$8:$D$104,'Deflatores Sisp'!G38,Funções!$K$8:$K$104) -> 0 | K38: =IF(H38="",COUNTIF(Funções!D$8:D$104,G38)*I38,H38*J38) -> 0 | M38: AIE
M39: EE
A40: Itens Não Mensuráveis | G40: Sigla | H40: Contribuição em PF Local | J40: Quantidade | K40: PF Local FS | M40: CE
A41: Contrato | B41: Descrição | F41: Origem | M41: SE
A42: SISP 2.3 | B42: Páginas Estáticas | F42: SISP – 4.11 Desenvolvimento, Manutenção e Publicação de Paginas Estáticas de Intranet, Internet ou Portal | G42: PAG | H42: 0.6 | J42: =COUNTIF(Funções!C$8:C$104,G42) -> 0 | K42: =SUMIF(Funções!C$8:C$104,$G42,Funções!N$8:N$104) -> 0 | M42: =""&G42 -> PAG
A43: PRODESP | B43: Conteúdo estático em sites ou Portais - neste item são considerados página e seus componentes internos, menus e arquivos para download (Incluídos e Alterados) | F43: Guia local - Edital com a Prodesp - PRO-7952 | G43: COSNF | H43: 0.6 | J43: =COUNTIF(Funções!C$8:C$104,G43) -> 0 | K43: =SUMIF(Funções!C$8:C$104,$G43,Funções!N$8:N$104) -> 0 | M43: =""&G43 -> COSNF
A44: PRODESP | B44: Conteúdo estático em sites ou Portais - neste item são considerados página e seus componentes internos, menus e arquivos para download (Excluídos) | F44: Guia local - Edital com a Prodesp - PRO-7952 | G44: COSNFE | H44: 0.02 | J44: =COUNTIF(Funções!C$8:C$104,G44) -> 0 | K44: =SUMIF(Funções!C$8:C$104,$G44,Funções!N$8:N$104) -> 0 | M44: =""&G44 -> COSNFE
A45: PRODESP | B45: Dados de Código - Inclusão de Tabela | F45: Guia local - Edital com a Prodesp - PRO-7952 | G45: DCDI | H45: 1 | J45: =COUNTIF(Funções!C$8:C$104,G45) -> 0 | K45: =SUMIF(Funções!C$8:C$104,$G45,Funções!N$8:N$104) -> 0 | M45: =""&G45 -> DCDI
A46: PRODESP | B46: Dados de Código -Alteração de Tabela | F46: Guia local - Edital com a Prodesp - PRO-7952 | G46: DCDA | H46: 0.6 | J46: =COUNTIF(Funções!C$8:C$104,G46) -> 0 | K46: =SUMIF(Funções!C$8:C$104,$G46,Funções!N$8:N$104) -> 0 | M46: =""&G46 -> DCDA
A47: PRODESP | B47: Dados de Código - Exclusão de Tabela | F47: Guia local - Edital com a Prodesp - PRO-7952 | G47: DCDE | H47: 0.4 | J47: =COUNTIF(Funções!C$8:C$104,G47) -> 0 | K47: =SUMIF(Funções!C$8:C$104,$G47,Funções!N$8:N$104) -> 0 | M47: =""&G47 -> DCDE
A48: PRODESP | B48: Dados de Código - Inclusão de funcionalidade | F48: Guia local - Edital com a Prodesp - PRO-7952 | G48: DCFI | H48: 1.5 | J48: =COUNTIF(Funções!C$8:C$104,G48) -> 0 | K48: =SUMIF(Funções!C$8:C$104,$G48,Funções!N$8:N$104) -> 0 | M48: =""&G48 -> DCFI
A49: PRODESP | B49: Dados de Código - Alteração de funcionalidade | F49: Guia local - Edital com a Prodesp - PRO-7952 | G49: DCFA | H49: 1.05 | J49: =COUNTIF(Funções!C$8:C$104,G49) -> 0 | K49: =SUMIF(Funções!C$8:C$104,$G49,Funções!N$8:N$104) -> 0 | M49: =""&G49 -> DCFA
A50: PRODESP | B50: Dados de Código - Exclusão de funcionalidade | F50: Guia local - Edital com a Prodesp - PRO-7952 | G50: DCFE | H50: 0.6 | J50: =COUNTIF(Funções!C$8:C$104,G50) -> 0 | K50: =SUMIF(Funções!C$8:C$104,$G50,Funções!N$8:N$104) -> 0 | M50: =""&G50 -> DCFE
A51: PRODESP | B51: Manutenção de Elastic Search (DATA LAKES)- Inclusão de Índice | F51: Guia local - Edital com a Prodesp - PRO-7952 | G51: DATDI | H51: 4.9 | J51: =COUNTIF(Funções!C$8:C$104,G51) -> 0 | K51: =SUMIF(Funções!C$8:C$104,$G51,Funções!N$8:N$104) -> 0 | M51: =""&G51 -> DATDI
A52: PRODESP | B52: Manutenção de Elastic Search (DATA LAKES) Alteração de Índice | F52: Guia local - Edital com a Prodesp - PRO-7952 | G52: DATDA | H52: 2.45 | J52: =COUNTIF(Funções!C$8:C$104,G52) -> 0 | K52: =SUMIF(Funções!C$8:C$104,$G52,Funções!N$8:N$104) -> 0 | M52: =""&G52 -> DATDA
A53: PRODESP | B53: Manutenção de Elastic Search (DATA LAKES) - Exclusão de Índice | F53: Guia local - Edital com a Prodesp - PRO-7952 | G53: DATDE | H53: 1.23 | J53: =COUNTIF(Funções!C$8:C$104,G53) -> 0 | K53: =SUMIF(Funções!C$8:C$104,$G53,Funções!N$8:N$104) -> 0 | M53: =""&G53 -> DATDE
... A58: PRODESP | B58: Pronto-atendimento - Contempla tarefas de pronto-atendimento (considera 10h = 1 PF) | F58: Guia local - Edital com a Prodesp - PRO-7952 | G58: PA | H58: 0.1 | J58: =COUNTIF(Funções!C$8:C$104,G58) -> 0 | K58: =SUMIF(Funções!C$8:C$104,$G58,Funções!N$8:N$104) -> 0 | M58: =""&G58 -> PA
G59: . | J59: =COUNTIF(Funções!C$8:C$104,G59) -> 0 | K59: =SUMIF(Funções!C$8:C$104,$G59,Funções!N$8:N$104) -> 0 | M59: =""&G59 -> .
G60: . | J60: =COUNTIF(Funções!C$8:C$104,G60) -> 0 | K60: =SUMIF(Funções!C$8:C$104,$G60,Funções!N$8:N$104) -> 0 | M60: =""&G60 -> .
G61: . | J61: =COUNTIF(Funções!C$8:C$104,G61) -> 0 | K61: =SUMIF(Funções!C$8:C$104,$G61,Funções!N$8:N$104) -> 0 | M61: =""&G61 -> .
G62: . | J62: =COUNTIF(Funções!C$8:C$104,G62) -> 0 | K62: =SUMIF(Funções!C$8:C$104,$G62,Funções!N$8:N$104) -> 0 | M62: =""&G62 -> .
G63: . | J63: =COUNTIF(Funções!C$8:C$104,G63) -> 0 | K63: =SUMIF(Funções!C$8:C$104,$G63,Funções!N$8:N$104) -> 0 | M63: =""&G63 -> .
G64: . | J64: =COUNTIF(Funções!C$8:C$104,G64) -> 0 | K64: =SUMIF(Funções!C$8:C$104,$G64,Funções!N$8:N$104) -> 0 | M64: =""&G64 -> .
G65: . | J65: =COUNTIF(Funções!C$8:C$104,G65) -> 0 | K65: =SUMIF(Funções!C$8:C$104,$G65,Funções!N$8:N$104) -> 0 | M65: =""&G65 -> .
G66: . | J66: =COUNTIF(Funções!C$8:C$104,G66) -> 0 | K66: =SUMIF(Funções!C$8:C$104,$G66,Funções!N$8:N$104) -> 0 | M66: =""&G66 -> .
G67: . | J67: =COUNTIF(Funções!C$8:C$104,G67) -> 0 | K67: =SUMIF(Funções!C$8:C$104,$G67,Funções!N$8:N$104) -> 0 | M67: =""&G67 -> .
G68: . | J68: =COUNTIF(Funções!C$8:C$104,G68) -> 0 | K68: =SUMIF(Funções!C$8:C$104,$G68,Funções!N$8:N$104) -> 0 | M68: =""&G68 -> .
G69: . | J69: =COUNTIF(Funções!C$8:C$104,G69) -> 0 | K69: =SUMIF(Funções!C$8:C$104,$G69,Funções!N$8:N$104) -> 0 | M69: =""&G69 -> .
G70: . | J70: =COUNTIF(Funções!C$8:C$104,G70) -> 0 | K70: =SUMIF(Funções!C$8:C$104,$G70,Funções!N$8:N$104) -> 0 | M70: =""&G70 -> .
